Workbook

Sheet Dashboard
A1: PhD EDGE COMPUTING RESEARCH PREPARATION & PROGRESS DASHBOARD
A3: 100% Free Open-Access Edition | Target: PhD Admissions | Duration: 24 Weeks (7-10 hrs/week) | Zero Paywalls
A5: PROGRAM PROGRESS | C5: TOTAL HOURS LOGGED | E5: TARGET HOURS | G5: COURSES COMPLETED | I5: PAPERS ANALYZED | K5: PhD READINESS INDEX
A6: =AVERAGE('Weekly Progress Tracker'!P5:P28) | C6: =SUM('Weekly Progress Tracker'!F5:F28) | E6: =SUM('Weekly Progress Tracker'!E5:E28) | G6: =COUNTIF('Course Tracker'!M4:M25, "Completed") | I6: =COUNTIF('Paper Tracker'!I5:I25, "Yes") | K6: ='PhD Readiness Assessment'!C21
A9: 24-WEEK RESEARCH PREPARATION ROADMAP & MONTHLY MILESTONES
A10: Month | B10: Weeks | C10: Core Focus Area | E10: Key Thematic Modules | H10: Milestone Tangible Deliverable | L10: Target Date | M10: Status
A11: Month 1 | B11: W1 - W4 | C11: Networking & Edge Foundations | E11: Edge Architecture, Network Virtualization, SDN, Protocols (TCP/UDP/MQTT), Wireless IoT | H11: Comprehensive Technical Taxonomy & Comparative Survey: Edge vs Fog vs Cloudlets | L11: Month 1 End | M11: In Progress
A12: Month 2 | B12: W5 - W8 | C12: Distributed Systems & Consensus | E12: Processes, RPC, Logical Clocks, Consistency Models, Raft Consensus, Distributed Storage | H12: Raft Consensus Node Implementation & Edge State Synchronization Protocol Critique | L12: Month 2 End | M12: Not Started
A13: Month 3 | B13: W9 - W12 | C13: Cloud-Native, K3s & Edge Arch | E13: Hypervisors vs Containers, K3s/KubeEdge Orchestration, Serverless Edge, Edge Topologies | H13: Edge-Native Microservice Cluster deployed on K3s with Latency & Resource Benchmarking | L13: Month 3 End | M13: Not Started
A14: Month 4 | B14: W13 - W16 | C14: 5G/6G MEC & Optimization | E14: 3GPP/ETSI MEC Standards, Network Slicing, URLLC, Task Offloading Models, Convex Optimization | H14: Formulation & CVXPY Implementation of Multi-Device Edge Computation Offloading Model | L14: Month 4 End | M14: Not Started
A15: Month 5 | B15: W17 - W20 | C15: Edge AI & Security/Privacy | E15: Model Compression, Quantization/Pruning, TinyML, Federated Learning (FedAvg), TEEs & Zero Trust | H15: Edge-Cloud Collaborative Inference & Differential Privacy Federated Learning Benchmark | L15: Month 5 End | M15: Not Started
A16: Month 6 | B16: W21 - W24 | C16: Simulation & PhD Proposal | E16: EdgeCloudSim, Discrete Event Modeling, Experimental Design, Academic Writing, Research Gaps | H16: Complete Edge Computing Research Paper / Capstone Report + PhD Research Proposal Draft | L16: Month 6 End | M16: Not Started
A18: WEEKLY TIME ALLOCATION TARGET (7 - 10 Hours/Week) | H18: WORKBOOK NAVIGATION DIRECTORY
A19: Structured Coursework & Theory | D19: 3.0 - 4.0 hrs | E19: 40% | F19: MIT/Stanford/Coursera free graduate lectures & readings | H19: Sheet 2: Master Curriculum | K19: Complete course directory across Levels 0-14 with strictly free resources
A20: Research Paper Reading & Analysis | D20: 2.0 - 2.5 hrs | E20: 25% | F20: Seminal papers, methodology deconstruction, gap finding | H20: Sheet 3: 24-Week Plan | K20: Comprehensive week-by-week curriculum, activities, deliverables, criteria
A21: Hands-on Systems Lab & Coding | D21: 1.5 - 2.0 hrs | E21: 20% | F21: K3s, Docker, Python CVXPY, TinyML, Raft implementation | H21: Sheet 4: Weekly Progress Tracker | K21: Log target vs actual hours, readings, labs, challenges, key learnings
A22: Research Methodology & Proposal Prep | D22: 1.0 - 1.5 hrs | E22: 15% | F22: LaTeX writing, RQ formulation, experimental design | H22: Sheet 5: Course Tracker | K22: Track enrolled free courses, URLs, progress %, ratings, milestones
A23: Total Weekly Investment | D23: 7.5 - 10.0 hrs | E23: 100% | F23: 100% Free Open-Access study plan tailored for PhD applicant | H23: Sheet 6: Paper Tracker | K23: 25+ seminal/modern open-access research papers, RQs, methodologies, gaps
H24: Sheet 7: Research Ideas (Idea Bank) | K24: Problem statements, research questions, methodologies for PhD proposal
H25: Sheet 8: Skills Matrix | K25: Current vs target competency levels (0-5) across 21 Edge research skills
H26: Sheet 9: Simulation & Tools Guide | K26: EdgeCloudSim, iFogSim, CloudSim, ns-3, Mininet, K3s open-source analysis
H27: Sheet 10: Recommended Path | K27: Curated Must Take, Strongly Recommended, Optional, Reference tiers (100% Free)
H28: Sheet 11: PhD Readiness Assessment | K28: 19-point rubric to evaluate readiness for top-tier PhD programs
A30: HONG KONG PhD CAMPAIGN (10-WEEK APPLICATION OVERLAY)
A31: TARGET UNIVERSITIES | C31: POTENTIAL SUPERVISORS | E31: TIER 1 MATCHES | G31: ACTIVE RECRUITING | I31: WEEKS REMAINING | K31: NEAREST DEADLINE
A32: 8 Universities | C32: 12 Discovered | E32: 10 Supervisors | G32: 11 Verified | I32: 9 Weeks | K32: 59 Days (Dec 1)

Sheet Master Curriculum
A1: MASTER CURRICULUM DIRECTORY — 100% STRICTLY FREE OPEN-ACCESS RESOURCES
A3: Level | B3: Module Name | C3: Topic | D3: Course / Resource Title | E3: Platform / Institution | F3: Instructor / Author | G3: URL | H3: Course Rating | I3: Review Count / Learners | J3: Last Updated | K3: Difficulty | L3: Duration (Hours) | M3: Cost / Access | N3: Academic Value (1-10) | O3: Technical Depth (1-10) | P3: Edge Relevance (1-10) | Q3: PhD Relevance (1-10) | R3: Value for Time (1-10) | S3: Overall Score (1-10) | T3: Selection Tier | U3: Recommended Week | V3: Status | W3: Selection Rationale & Notes
A4: Level 0 | B4: Orientation | C4: Edge & Fog Computing Concepts | D4: Introduction to Edge Computing (LF Edge) | E4: LF Edge / Linux Foundation | F4: LF Edge & CNCF Community | G4: https://www.lfedge.org/resources/whitepapers/ | H4: 4.7 | I4: 15,000+ | J4: 2024 | K4: Foundational | L4: 10 | M4: 100% Free Open Access | N4: 8 | O4: 7 | P4: 10 | Q4: 8 | R4: 9 | S4: =ROUND((N4*0.20 + O4*0.20 + P4*0.25 + Q4*0.25 + R4*0.10), 1) | T4: Must Take | U4: Week 1 | V4: In Progress | W4: Canonical industry primer from Linux Foundation detailing LF Edge umbrella and architecture.
A5: Level 0 | B5: Orientation | C5: Device-Edge-Cloud Hierarchy | D5: Edge Computing: Vision and Challenges (Open Access) | E5: IEEE IoT Journal / Wayne State | F5: Prof. Weisong Shi | G5: https://doi.org/10.1109/JIOT.2016.2579198 | H5: 4.9 | I5: 8,500+ Cites | J5: Seminal (2016) | K5: Intermediate | L5: 6 | M5: 100% Free Open Paper | N5: 10 | O5: 8 | P5: 10 | Q5: 10 | R5: 10 | S5: =ROUND((N5*0.20 + O5*0.20 + P5*0.25 + Q5*0.25 + R5*0.10), 1) | T5: Must Take | U5: Week 1 | V5: Not Started | W5: Essential foundational reading for every Edge Computing researcher. Establishes core taxonomy.
A6: Level 1 | B6: Networking | C6: Internet Architecture & TCP/IP | D6: CS144: Introduction to Computer Networking | E6: Stanford University | F6: Prof. Philip Levis & Keith Winstein | G6: https://cs144.github.io/ | H6: 4.9 | I6: Stanford Core | J6: 2024 | K6: Intermediate | L6: 35 | M6: 100% Free OpenCourseWare | N6: 10 | O6: 10 | P6: 9 | Q6: 10 | R6: 9 | S6: =ROUND((N6*0.20 + O6*0.20 + P6*0.25 + Q6*0.25 + R6*0.10), 1) | T6: Must Take | U6: Week 2 | V6: Not Started | W6: Rigorous graduate-level networking foundation. Emphasizes transport layers, buffers, and latency.
A7: Level 1 | B7: Networking | C7: Software-Defined Networking (SDN) | D7: Software-Defined Networking (CS6250) | E7: Georgia Tech (OMSCS) / YouTube | F7: Prof. Nick Feamster | G7: https://www.youtube.com/playlist?list=PLAwxTw4SYaPkA_TlycMocPkWz_aQn_zXw | H7: 4.8 | I7: 25,000+ OMSCS | J7: 2023 | K7: Intermediate | L7: 25 | M7: 100% Free Full Lectures | N7: 9 | O7: 9 | P7: 9 | Q7: 9 | R7: 9 | S7: =ROUND((N7*0.20 + O7*0.20 + P7*0.25 + Q7*0.25 + R7*0.10), 1) | T7: Strongly Recommended | U7: Week 3 | V7: Not Started | W7: Teaches OpenFlow, programmable data planes, and network control planes critical for edge slicing.
A8: Level 1 | B8: Networking | C8: Wireless Networks & Protocols | D8: Computer Networks: A Top-Down Approach (Lectures) | E8: UMass Amherst | F8: Prof. Jim Kurose & Keith Ross | G8: https://gaia.cs.umass.edu/kurose_ross/online_lectures.htm | H8: 4.9 | I8: 50,000+ | J8: 2023 | K8: Foundational | L8: 20 | M8: 100% Free Video Lectures | N8: 9 | O8: 8 | P8: 8 | Q8: 8 | R8: 9 | S8: =ROUND((N8*0.20 + O8*0.20 + P8*0.25 + Q8*0.25 + R8*0.10), 1) | T8: Reference Only | U8: Week 2 | V8: Not Started | W8: The gold standard in network theory. Complete author video lectures covering transport and wireless.
A9: Level 2 | B9: Distributed Systems | C9: Consensus, RPC & Replication | D9: 6.5840 / 6.824: Distributed Systems | E9: MIT CSAIL / YouTube | F9: Prof. Robert Morris | G9: https://pdos.csail.mit.edu/6.824/ | H9: 5.0 | I9: Global Benchmark | J9: 2024 | K9: Advanced | L9: 45 | M9: 100% Free Full Lectures & Labs | N9: 10 | O9: 10 | P9: 10 | Q9: 10 | R9: 9 | S9: =ROUND((N9*0.20 + O9*0.20 + P9*0.25 + Q9*0.25 + R9*0.10), 1) | T9: Must Take | U9: Weeks 5-8 | V9: Not Started | W9: The single most important distributed systems course in the world. Mandatory for Edge systems research.
A10: Level 2 | B10: Distributed Systems | C10: Distributed Systems Theory & Principles | D10: Distributed Systems Course (Cambridge) | E10: University of Cambridge / YouTube | F10: Dr. Martin Kleppmann | G10: https://www.youtube.com/playlist?list=PLeKd45zvjcDFUEv_ohr_HdUFe97RItdyB | H10: 5.0 | I10: Authoritative | J10: 2023 | K10: Advanced | L10: 20 | M10: 100% Free Full Course | N10: 10 | O10: 10 | P10: 9 | Q10: 10 | R10: 10 | S10: =ROUND((N10*0.20 + O10*0.20 + P10*0.25 + Q10*0.25 + R10*0.10), 1) | T10: Must Take | U10: Weeks 6-8 | V10: Not Started | W10: Flawless coverage of replication, partitioning, transactions, logical clocks, and consensus.
A11: Level 2 | B11: Distributed Systems | C11: Cloud Concepts & Distributed Protocols | D11: Cloud Computing Concepts (Part 1 & 2) | E11: UIUC / Coursera (Free Audit) | F11: Prof. Indranil Gupta | G11: https://www.coursera.org/learn/cloud-computing | H11: 4.8 | I11: 60,000+ | J11: 2023 | K11: Intermediate | L11: 30 | M11: 100% Free Audit Mode | N11: 9 | O11: 9 | P11: 9 | Q11: 9 | R11: 9 | S11: =ROUND((N11*0.20 + O11*0.20 + P11*0.25 + Q11*0.25 + R11*0.10), 1) | T11: Strongly Recommended | U11: Weeks 5-7 | V11: Not Started | W11: Covers gossip protocols, membership algorithms, Paxos, Raft, and distributed mutual exclusion.
A12: Level 3 | B12: Cloud Computing | C12: Cloud Architecture & IaaS/PaaS | D12: Cloud Computing Specialization | E12: UIUC / Coursera (Free Audit) | F12: Prof. Indranil Gupta et al. | G12: https://www.coursera.org/specializations/cloud-computing | H12: 4.7 | I12: 120,000+ | J12: 2023 | K12: Intermediate | L12: 35 | M12: 100% Free Audit Mode | N12: 9 | O12: 8 | P12: 8 | Q12: 8 | R12: 8 | S12: =ROUND((N12*0.20 + O12*0.20 + P12*0.25 + Q12*0.25 + R12*0.10), 1) | T12: Strongly Recommended | U12: Week 9 | V12: Not Started | W12: Connects core cloud architectures to distributed systems. Contextualizes the cloud layer in Edge-Cloud.
A13: Level 3 | B13: Cloud Computing | C13: Serverless & Microservice Arch | D13: Serverless Computing & Microservices Guide | E13: AWS Serverless Land | F13: AWS Architecture Team | G13: https://serverlessland.com/ | H13: 4.6 | I13: 40,000+ | J13: 2024 | K13: Intermediate | L13: 12 | M13: 100% Free Open Guides & Code | N13: 8 | O13: 8 | P13: 8 | Q13: 7 | R13: 8 | S13: =ROUND((N13*0.20 + O13*0.20 + P13*0.25 + Q13*0.25 + R13*0.10), 1) | T13: Optional | U13: Week 11 | V13: Not Started | W13: Explores FaaS execution models, event-driven triggers, and cold-start mitigations relevant to Edge FaaS.
A14: Level 4 | B14: Internet of Things | C14: IoT Architecture & Embedded Comms | D14: Introduction to the Internet of Things (IoT) | E14: Curtin University / edX (Free Audit) | F14: Prof. Iain Murray | G14: https://www.edx.org/learn/iot-internet-of-things/curtin-university-introduction-to-the-internet-of-things-iot | H14: 4.6 | I14: 35,000+ | J14: 2023 | K14: Intermediate | L14: 18 | M14: 100% Free Audit Mode | N14: 8 | O14: 8 | P14: 9 | Q14: 8 | R14: 8 | S14: =ROUND((N14*0.20 + O14*0.20 + P14*0.25 + Q14*0.25 + R14*0.10), 1) | T14: Strongly Recommended | U14: Week 4 | V14: Not Started | W14: Strong engineering grounding in sensors, actuators, edge gateways, MQTT, and CoAP messaging.
A15: Level 4 | B15: Internet of Things | C15: Industrial IoT & Edge Intelligence | D15: Industrial Internet of Things (IIoT) | E15: UC San Diego / Coursera (Free Audit) | F15: Prof. Derek Snyder | G15: https://www.coursera.org/learn/industrial-internet-of-things | H15: 4.5 | I15: 18,000+ | J15: 2023 | K15: Intermediate | L15: 15 | M15: 100% Free Audit Mode | N15: 8 | O15: 7 | P15: 8 | Q15: 7 | R15: 8 | S15: =ROUND((N15*0.20 + O15*0.20 + P15*0.25 + Q15*0.25 + R15*0.10), 1) | T15: Optional | U15: Week 4 | V15: Not Started | W15: Focuses on high-reliability edge telemetry, SCADA integration, and time-sensitive networking.
... A34: Level 13 | B34: Research Methods | C34: LaTeX & Technical Documentation | D34: Overleaf LaTeX Tutorial & Research Templates | E34: Overleaf / Digital Science | F34: Overleaf Academic Team | G34: https://www.overleaf.com/learn | H34: 4.9 | I34: Global Standard | J34: 2024 | K34: Foundational | L34: 8 | M34: 100% Free Open Tutorials | N34: 8 | O34: 8 | P34: 7 | Q34: 9 | R34: 10 | S34: =ROUND((N34*0.20 + O34*0.20 + P34*0.25 + Q34*0.25 + R34*0.10), 1) | T34: Must Take | U34: Week 23 | V34: Not Started | W34: Standard authoring environment for IEEE and ACM conference papers and PhD thesis proposals.

Sheet 24-Week Plan
A1: 24-WEEK STRUCTURED EDGE COMPUTING RESEARCH PROGRAM
A3: Week | B3: Dates / Phase | C3: Module / Level | D3: Thematic Topic | E3: Learning Objectives | F3: Primary Course / Study Material | G3: Secondary Resource / Videos | H3: Research Paper Reading | I3: Practical Hands-on Activity | J3: Research Methodology Activity | K3: Target Hours | L3: Expected Deliverable | M3: Completion Criteria | N3: Status | O3: Reflections & Notes
A4: 1 | B4: Month 1 - W1 | C4: Level 0: Orientation | D4: Edge Computing Paradigm & Device-Edge-Cloud Continuum | E4: Deconstruct edge computing definitions, why latency/bandwidth necessitate edge, and differentiate Cloudlets, Fog, and MEC. | F4: LF Edge: Open Architecture & Whitepapers (Free) | G4: IEEE ComSoc Edge Open Tutorials | H4: Shi et al. (2016) 'Edge Computing: Vision and Challenges' (Open Access) | I4: Architectural Mapping: Diagram 3 real-world topologies (Connected Autonomous Vehicle, Smart Factory, Remote Healthcare). | J4: Literature Synthesis: Write a 1-page critique summarizing the driving physical and economic constraints of Edge Computing. | K4: 8 | L4: 1-Page Research Memorandum: 'Why Edge Computing is Inevitable' | M4: Clear taxonomy diagram + 1-page paper critique completed | N4: In Progress
A5: 2 | B5: Month 1 - W2 | C5: Level 1: Networking | D5: Transport Protocols, Latency & Bandwidth-Delay Product | E5: Analyze TCP vs UDP behavior in edge networks, bufferbloat, jitter, tail latency, and packet loss impact on real-time apps. | F5: Stanford CS144: Intro to Computer Networking (Free OpenCourseWare) | G5: Kurose & Ross Free Author Video Lectures | H5: Satyanarayanan (2009) 'The Case for VM-Based Cloudlets in Mobile Computing' (Open Access) | I5: Network Emulation: Measure round-trip time (RTT) and jitter using ping/iperf3 under simulated packet loss and throttling. | J5: Methodology: Extract experimental setups and network metric definitions from Satyanarayanan (2009). | K5: 8.5 | L5: Network Latency & Throughput Benchmark Report | M5: Hands-on iperf3 logs + Cloudlet latency analysis complete | N5: Not Started
A6: 3 | B6: Month 1 - W3 | C6: Level 1: Networking | D6: Software-Defined Networking (SDN) & Programmable Planes | E6: Understand decoupling of control and data planes, OpenFlow, and how SDN enables dynamic edge traffic steering. | F6: Georgia Tech CS6250: SDN (Free Full Video Lectures) | G6: P4 Language Tutorials (p4.org Free) | H6: Kreutz et al. (2015) 'Software-Defined Networking: A Comprehensive Survey' (Open Access) | I6: Mininet Lab: Build a custom 4-switch topology in Mininet and write a simple OpenFlow controller rule to redirect edge traffic. | J6: Research Design: Identify how SDN controllers address dynamic failover in multi-edge server topologies. | K6: 8.5 | L6: Mininet OpenFlow Controller Python Script & Topology Map | M6: Working Mininet traffic redirection script verified | N6: Not Started
A7: 4 | B7: Month 1 - W4 | C7: Level 1/4: Wireless & IoT | D7: Cellular Data, MQTT, CoAP & Time-Sensitive Networking | E7: Evaluate constrained application protocols (MQTT vs CoAP vs HTTP/2), QoS levels, and cellular wireless links (4G/5G NR). | F7: Curtin Univ IoT (edX Free Audit) | G7: OASIS MQTT v5.0 Open Specification Guide | H7: Al-Fuqaha et al. (2015) 'Internet of Things: A Survey on Enabling Technologies, Protocols, and Applications' (Open Access) | I7: Protocol Benchmarking: Deploy EMQX/Mosquitto broker and publish 1,000 telemetry messages under MQTT QoS 0, 1, 2. | J7: Month 1 Milestone Synthesis: Compile Level 0-1 insights into a comprehensive Edge Networking Architecture Reference. | K7: 9 | L7: Month 1 Milestone: Edge Protocols & Networking Whitepaper | M7: MQTT QoS latency benchmark chart + Month 1 Milestone delivered | N7: Not Started
A8: 5 | B8: Month 2 - W5 | C8: Level 2: Dist Systems | D8: Distributed Processes, RPC & Logical Clocks | E8: Master RPC mechanisms (gRPC), process failure models, Lamport timestamps, and Vector clocks in decentralized systems. | F8: MIT 6.824: Distributed Systems (Free CSAIL Lectures 1-3 & Lab 1) | G8: Martin Kleppmann Free Distributed Systems Series | H8: Lamport (1978) 'Time, Clocks, and the Ordering of Events in a Distributed System' (Open CACM) | I8: Go / Python Lab: Implement a multi-threaded RPC client-server application with logical clock timestamp tracking. | J8: Paper Deconstruction: Analyze Lamport's partial ordering proofs and explain why clock synchronization fails across edge nodes. | K8: 8.5 | L8: Working RPC & Vector Clock Python/Go Implementation | M8: Working code repository + Lamport proof breakdown completed | N8: Not Started
A9: 6 | B9: Month 2 - W6 | C9: Level 2: Dist Systems | D9: Consistency Models, Replication & CAP Theorem | E9: Deep dive into Strong Consistency vs Eventual Consistency, Linearizability, Session Guarantees, and PACELC theorem. | F9: MIT 6.824 (Free Lectures 4-6: GFS & Replication) | G9: Kleppmann Cambridge Lectures on Consistency & Replication | H9: Vogels (2009) 'Eventually Consistent' (Open Access) + Gilbert & Lynch CAP Proof | I9: Database Replication Lab: Configure a 3-node Redis/etcd replica set and observe behavior during simulated network partitions. | J9: Research Question Formulation: Draft 2 research questions exploring consistency vs latency trade-offs at the edge. | K9: 8.5 | L9: Consistency & Partition Tolerance Empirical Analysis | M9: Redis partition test results + 2 PhD-level RQs formulated | N9: Not Started
A10: 7 | B10: Month 2 - W7 | C10: Level 2: Dist Systems | D10: Distributed Consensus: Paxos & Raft Frameworks | E10: Understand state machine replication, leader election, log replication, safety invariants, and joint consensus in Raft. | F10: MIT 6.824 (Free Lectures 7-8: Raft Consensus & Lab 2A) | G10: Ongaro & Ousterhout Raft Interactive Visualization (Free) | H10: Ongaro & Ousterhout (2014) 'In Search of an Understandable Consensus Algorithm' (Open USENIX ATC) | I10: Raft Implementation Lab: Implement or step through leader election and heartbeat timeouts in Go/Python. | J10: Comparative Analysis: Compare Raft message complexity vs Byzantine Fault Tolerance (BFT) in resource-limited edge nodes. | K10: 9 | L10: Raft Leader Election Prototype & Complexity Comparison | M10: Raft state machine unit tests passing + complexity table written | N10: Not Started
A11: 8 | B11: Month 2 - W8 | C11: Level 2: Dist Systems | D11: Distributed Storage, Fault Tolerance & Edge State | E11: Examine sharding, consistent hashing, CRDTs (Conflict-free Replicated Data Types), and failure recovery mechanisms. | F11: MIT 6.824 (Free Lectures 9-11: Sharding & Fault Tolerance) | G11: Kleppmann Cambridge Lectures on CRDTs (Free) | H11: Shapiro et al. (2011) 'Conflict-Free Replicated Data Types' (Open INRIA) | I11: CRDT Implementation: Implement an operation-based PN-Counter or G-Set in Python to merge disconnected edge states. | J11: Month 2 Milestone Synthesis: Write a formal evaluation of distributed consensus feasibility on edge nodes. | K11: 9 | L11: Month 2 Milestone: Edge Consensus & State Sync Technical Report | M11: CRDT Python script + Month 2 Milestone report completed | N11: Not Started
A12: 9 | B12: Month 3 - W9 | C12: Level 3/5: Containers | D12: Containerization Internals (cgroups, namespaces, overlayFS) | E12: Understand OS-level virtualization vs hypervisors, container security isolation, and memory/CPU limits on edge devices. | F12: Linux Containers from Scratch (Liz Rice Open Code & Tutorial) | G12: Linux Kernel Documentation on cgroups v2 (Free) | H12: Felter et al. (2015) 'An Updated Performance Comparison of Virtual Machines and Linux Containers' (Open Access) | I12: Container Internals Lab: Manually create an isolated process container using Linux `unshare`, `chroot`, and `cgroups`. | J12: Benchmarking Methodology: Measure cold-start time and memory footprint of Docker vs microVM (Firecracker). | K12: 8.5 | L12: Container vs VM Virtualization Benchmark Report | M12: Linux cgroup isolation lab verified + benchmark report logged | N12: Not Started
A13: 10 | B13: Month 3 - W10 | C13: Level 5/6: K8s / K3s | D13: Edge Kubernetes & Lightweight Cluster Orchestration | E13: Deploy lightweight Kubernetes (K3s, KubeEdge) and study edge node autonomy, pod scheduling, and worker detachment. | F13: LFS156x: Intro to Kubernetes on Edge with K3s (edX Free Audit) | G13: KubeEdge Official Open Architecture Documentation | H13: Xiong et al. (2018) 'Extend Cloud to Edge with KubeEdge' (Open Access) | I13: K3s Cluster Lab: Deploy a 2-node K3s cluster (1 control plane, 1 edge agent) using VMs or Raspberry Pis. | J13: Scheduling Analysis: Evaluate how K8s default scheduler behaves when edge nodes experience intermittent disconnects. | K13: 9 | L13: Running Multi-Node K3s Cluster & Deployment Manifests | M13: Functional K3s edge cluster + deployment YAMLs validated | N13: Not Started
A14: 11 | B14: Month 3 - W11 | C14: Level 6: Serverless | D14: Edge Serverless, FaaS Runtimes & Cold-Start Latency | E14: Investigate Function-as-a-Service (FaaS) models at the edge (OpenFaaS, Knative), event-driven execution, and cold-start mitigations. | F14: ServerlessLand Open Guides & Architecture Patterns | G14: OpenFaaS Open Source Workshop Docs | H14: Li et al. (2022) 'Serverless Computing on Gaussion Edge: A Survey' (Open Access arXiv) | I14: Serverless Edge Deployment: Deploy OpenFaaS on K3s and benchmark execution latency of Python functions under warm vs cold starts. | J14: Literature Gap Identification: Identify 3 unaddressed challenges in Edge Serverless function pre-warming. | K14: 8.5 | L14: OpenFaaS Function Benchmark & Cold-Start Analysis | M14: OpenFaaS invocation latency curves + 3 research gaps documented | N14: Not Started
A15: 12 | B15: Month 3 - W12 | C15: Level 7: Edge Core | D15: Edge-Cloud Collaboration, Hierarchical Topology & Orchestration | E15: Synthesize hierarchical edge-fog-cloud architectures, service placement strategies, and edge resource registries. | F15: Cloudbus Open Papers & Fog Paradigms (Prof. Buyya) | G15: ETSI MEC Open Architecture Spec GS MEC 003 | H15: Mao et al. (2017) 'A Survey on Mobile Edge Computing: The Communication Perspective' (Open Access) | I15: Topology Modeling: Design an end-to-end multi-tier simulation architecture in Python for IoT sensor-to-edge-to-cloud dataflow. | J15: Month 3 Milestone Synthesis: Write a comprehensive systems review on Edge Container Orchestration trade-offs. | K15: 9.5 | L15: Month 3 Milestone: Cloud-Native Edge Systems & Orchestration Survey | M15: Full multi-tier topology script + Month 3 Milestone delivered | N15: Not Started
... A27: 24 | B27: Month 6 - W24 | C27: Level 13: PhD Proposal | D27: PhD Research Proposal Synthesis & Statement of Purpose Defense | E27: Synthesize all 6 months of research, formulate a compelling 3-year PhD research proposal, and align with potential faculty advisors. | F27: University PhD Proposal Guidelines (MIT, Stanford, Cambridge, ETH Zurich) | G27: Overleaf Open Research Proposal Template | H27: Seminal & Visionary Open Papers: Satyanarayanan (2017), Shi (2016), Saad (2020) | I27: Proposal Drafting: Write a comprehensive 5-page PhD Research Proposal containing: Background, Problem Statement, RQs, Proposed Methodology, Timeline. | J27: Readiness Evaluation: Complete the Sheet 11 PhD Readiness Assessment rubric and compile targeted PhD supervisor outreach list. | K27: 10 | L27: Final Deliverable: Complete PhD Research Proposal + Target Supervisor Dossier | M27: Polished PhD Proposal PDF + completed Readiness Assessment | N27: Not Started

Sheet Weekly Progress Tracker
A1: WEEKLY PROGRESS & STUDY LOG TRACKER (24 WEEKS)
A3: Log weekly hours, research milestones, lab deliverables, and reflect on challenges to build academic rigor.
A4: Week | B4: Start Date | C4: End Date | D4: Main Topic | E4: Target Hours | F4: Actual Total Hours | G4: Course Hours | H4: Reading Hours | I4: Practical Hours | J4: Research Hours | K4: Papers Read | L4: Labs Completed | M4: Research Tasks Completed | N4: Weekly Goal | O4: Goal Achieved? | P4: Completion % | Q4: Challenges Encountered | R4: Key Learnings & Insights | S4: Next Week Focus
A5: Week 1 | B5: =DATE(2026,9,1)+(1-1)*7 | C5: =B5+6 | D5: Edge Paradigm & Device-Edge-Cloud Continuum | E5: 8.5 | F5: =SUM(G5:J5) | G5: 3.5 | H5: 2 | I5: 1.5 | J5: 1 | K5: 1 | L5: 1 | M5: 1 | N5: Deconstruct Edge vs Fog and map 3 architectures | O5: Yes | P5: 1 | Q5: Differentiating nuances between Cloudlets and MEC standards | R5: Edge is complementary to Cloud; driven by physical speed-of-light constraints. | S5: Deep dive into TCP/UDP latency and bufferbloat in CS144
A6: Week 2 | B6: =DATE(2026,9,1)+(2-1)*7 | C6: =B6+6 | D6: Transport Protocols, Latency & BDP | E6: 8.5 | F6: =SUM(G6:J6) | G6: 0 | H6: 0 | I6: 0 | J6: 0 | K6: 0 | L6: 0 | M6: 0 | N6: Master Transport Protocols, Latency & BDP and complete milestone | O6: No | P6: 0
A7: Week 3 | B7: =DATE(2026,9,1)+(3-1)*7 | C7: =B7+6 | D7: SDN & Programmable Data Planes | E7: 8.5 | F7: =SUM(G7:J7) | G7: 0 | H7: 0 | I7: 0 | J7: 0 | K7: 0 | L7: 0 | M7: 0 | N7: Master SDN & Programmable Data Planes and complete milestone | O7: No | P7: 0
A8: Week 4 | B8: =DATE(2026,9,1)+(4-1)*7 | C8: =B8+6 | D8: Wireless Protocols, MQTT/CoAP & Edge Telemetry | E8: 9 | F8: =SUM(G8:J8) | G8: 0 | H8: 0 | I8: 0 | J8: 0 | K8: 0 | L8: 0 | M8: 0 | N8: Master Wireless Protocols, MQTT/CoAP & Edge Telemetry and complete milestone | O8: No | P8: 0
A9: Week 5 | B9: =DATE(2026,9,1)+(5-1)*7 | C9: =B9+6 | D9: Distributed Processes, RPC & Logical Clocks | E9: 8.5 | F9: =SUM(G9:J9) | G9: 0 | H9: 0 | I9: 0 | J9: 0 | K9: 0 | L9: 0 | M9: 0 | N9: Master Distributed Processes, RPC & Logical Clocks and complete milestone | O9: No | P9: 0
A10: Week 6 | B10: =DATE(2026,9,1)+(6-1)*7 | C10: =B10+6 | D10: Consistency Models, Replication & CAP Theorem | E10: 8.5 | F10: =SUM(G10:J10) | G10: 0 | H10: 0 | I10: 0 | J10: 0 | K10: 0 | L10: 0 | M10: 0 | N10: Master Consistency Models, Replication & CAP Theorem and complete milestone | O10: No | P10: 0
A11: Week 7 | B11: =DATE(2026,9,1)+(7-1)*7 | C11: =B11+6 | D11: Distributed Consensus: Paxos & Raft | E11: 8.5 | F11: =SUM(G11:J11) | G11: 0 | H11: 0 | I11: 0 | J11: 0 | K11: 0 | L11: 0 | M11: 0 | N11: Master Distributed Consensus: Paxos & Raft and complete milestone | O11: No | P11: 0
A12: Week 8 | B12: =DATE(2026,9,1)+(8-1)*7 | C12: =B12+6 | D12: Distributed Storage, CRDTs & Fault Tolerance | E12: 9 | F12: =SUM(G12:J12) | G12: 0 | H12: 0 | I12: 0 | J12: 0 | K12: 0 | L12: 0 | M12: 0 | N12: Master Distributed Storage, CRDTs & Fault Tolerance and complete milestone | O12: No | P12: 0
A13: Week 9 | B13: =DATE(2026,9,1)+(9-1)*7 | C13: =B13+6 | D13: Containerization Internals (cgroups, namespaces) | E13: 8.5 | F13: =SUM(G13:J13) | G13: 0 | H13: 0 | I13: 0 | J13: 0 | K13: 0 | L13: 0 | M13: 0 | N13: Master Containerization Internals (cgroups, namespaces) and complete milestone | O13: No | P13: 0
A14: Week 10 | B14: =DATE(2026,9,1)+(10-1)*7 | C14: =B14+6 | D14: Edge Kubernetes & K3s Cluster Orchestration | E14: 8.5 | F14: =SUM(G14:J14) | G14: 0 | H14: 0 | I14: 0 | J14: 0 | K14: 0 | L14: 0 | M14: 0 | N14: Master Edge Kubernetes & K3s Cluster Orchestration and complete milestone | O14: No | P14: 0
A15: Week 11 | B15: =DATE(2026,9,1)+(11-1)*7 | C15: =B15+6 | D15: Edge Serverless, FaaS & Cold-Start Latency | E15: 8.5 | F15: =SUM(G15:J15) | G15: 0 | H15: 0 | I15: 0 | J15: 0 | K15: 0 | L15: 0 | M15: 0 | N15: Master Edge Serverless, FaaS & Cold-Start Latency and complete milestone | O15: No | P15: 0
A16: Week 12 | B16: =DATE(2026,9,1)+(12-1)*7 | C16: =B16+6 | D16: Edge-Cloud Collaboration & Hierarchical Arch | E16: 9 | F16: =SUM(G16:J16) | G16: 0 | H16: 0 | I16: 0 | J16: 0 | K16: 0 | L16: 0 | M16: 0 | N16: Master Edge-Cloud Collaboration & Hierarchical Arch and complete milestone | O16: No | P16: 0
A17: Week 13 | B17: =DATE(2026,9,1)+(13-1)*7 | C17: =B17+6 | D17: 5G Core, Network Slicing & ETSI MEC | E17: 8.5 | F17: =SUM(G17:J17) | G17: 0 | H17: 0 | I17: 0 | J17: 0 | K17: 0 | L17: 0 | M17: 0 | N17: Master 5G Core, Network Slicing & ETSI MEC and complete milestone | O17: No | P17: 0
A18: Week 14 | B18: =DATE(2026,9,1)+(14-1)*7 | C18: =B18+6 | D18: 6G Vision, URLLC & Vehicular Edge (V2X) | E18: 8.5 | F18: =SUM(G18:J18) | G18: 0 | H18: 0 | I18: 0 | J18: 0 | K18: 0 | L18: 0 | M18: 0 | N18: Master 6G Vision, URLLC & Vehicular Edge (V2X) and complete milestone | O18: No | P18: 0
A19: Week 15 | B19: =DATE(2026,9,1)+(15-1)*7 | C19: =B19+6 | D19: Computation Offloading Decision Models | E19: 8.5 | F19: =SUM(G19:J19) | G19: 0 | H19: 0 | I19: 0 | J19: 0 | K19: 0 | L19: 0 | M19: 0 | N19: Master Computation Offloading Decision Models and complete milestone | O19: No | P19: 0
A20: Week 16 | B20: =DATE(2026,9,1)+(16-1)*7 | C20: =B20+6 | D20: Convex Optimization & CVXPY Implementation | E20: 9 | F20: =SUM(G20:J20) | G20: 0 | H20: 0 | I20: 0 | J20: 0 | K20: 0 | L20: 0 | M20: 0 | N20: Master Convex Optimization & CVXPY Implementation and complete milestone | O20: No | P20: 0
A21: Week 17 | B21: =DATE(2026,9,1)+(17-1)*7 | C21: =B21+6 | D21: Edge AI Taxonomy, Quantization & Pruning | E21: 8.5 | F21: =SUM(G21:J21) | G21: 0 | H21: 0 | I21: 0 | J21: 0 | K21: 0 | L21: 0 | M21: 0 | N21: Master Edge AI Taxonomy, Quantization & Pruning and complete milestone | O21: No | P21: 0
A22: Week 18 | B22: =DATE(2026,9,1)+(18-1)*7 | C22: =B22+6 | D22: TinyML Deployments & Embedded Neural Inference | E22: 8.5 | F22: =SUM(G22:J22) | G22: 0 | H22: 0 | I22: 0 | J22: 0 | K22: 0 | L22: 0 | M22: 0 | N22: Master TinyML Deployments & Embedded Neural Inference and complete milestone | O22: No | P22: 0
A23: Week 19 | B23: =DATE(2026,9,1)+(19-1)*7 | C23: =B23+6 | D23: Federated Learning (FedAvg) & Non-IID Skew | E23: 8.5 | F23: =SUM(G23:J23) | G23: 0 | H23: 0 | I23: 0 | J23: 0 | K23: 0 | L23: 0 | M23: 0 | N23: Master Federated Learning (FedAvg) & Non-IID Skew and complete milestone | O23: No | P23: 0
A24: Week 20 | B24: =DATE(2026,9,1)+(20-1)*7 | C24: =B24+6 | D24: Edge Security, TEEs (TrustZone) & FL Privacy | E24: 9 | F24: =SUM(G24:J24) | G24: 0 | H24: 0 | I24: 0 | J24: 0 | K24: 0 | L24: 0 | M24: 0 | N24: Master Edge Security, TEEs (TrustZone) & FL Privacy and complete milestone | O24: No | P24: 0
A25: Week 21 | B25: =DATE(2026,9,1)+(21-1)*7 | C25: =B25+6 | D25: Discrete-Event Simulation with EdgeCloudSim | E25: 8.5 | F25: =SUM(G25:J25) | G25: 0 | H25: 0 | I25: 0 | J25: 0 | K25: 0 | L25: 0 | M25: 0 | N25: Master Discrete-Event Simulation with EdgeCloudSim and complete milestone | O25: No | P25: 0
A26: Week 22 | B26: =DATE(2026,9,1)+(22-1)*7 | C26: =B26+6 | D26: Capstone I: Experimental Design & Benchmark | E26: 8.5 | F26: =SUM(G26:J26) | G26: 0 | H26: 0 | I26: 0 | J26: 0 | K26: 0 | L26: 0 | M26: 0 | N26: Master Capstone I: Experimental Design & Benchmark and complete milestone | O26: No | P26: 0
A27: Week 23 | B27: =DATE(2026,9,1)+(23-1)*7 | C27: =B27+6 | D27: Capstone II: Result Analysis & LaTeX Paper | E27: 10 | F27: =SUM(G27:J27) | G27: 0 | H27: 0 | I27: 0 | J27: 0 | K27: 0 | L27: 0 | M27: 0 | N27: Master Capstone II: Result Analysis & LaTeX Paper and complete milestone | O27: No | P27: 0
A28: Week 24 | B28: =DATE(2026,9,1)+(24-1)*7 | C28: =B28+6 | D28: PhD Research Proposal Synthesis & Defense | E28: 10 | F28: =SUM(G28:J28) | G28: 0 | H28: 0 | I28: 0 | J28: 0 | K28: 0 | L28: 0 | M28: 0 | N28: Master PhD Research Proposal Synthesis & Defense and complete milestone | O28: No | P28: 0
A29: TOTAL / SUMMARY | D29: 24 WEEKS PROGRAM TOTALS | E29: =SUM(E5:E28) | F29: =SUM(F5:F28) | G29: =SUM(G5:G28) | H29: =SUM(H5:H28) | I29: =SUM(I5:I28) | J29: =SUM(J5:J28) | K29: =SUM(K5:K28) | L29: =SUM(L5:L28) | M29: =SUM(M5:M28) | P29: =AVERAGE(P5:P28)

Sheet Course Tracker
A1: ENROLLED COURSE PROGRESS & MILESTONE TRACKER (100% FREE RESOURCES)
A3: Course Title | B3: Platform / University | C3: Thematic Module | D3: Course URL | E3: Start Date | F3: Target Completion Date | G3: Actual Completion Date | H3: Estimated Hours | I3: Actual Hours Logged | J3: Progress % | K3: My Rating (1-5) | L3: Resource Type | M3: Status | N3: Key Takeaways & Notes
A4: Introduction to Edge Computing (LF Edge) | B4: LF Edge / Linux Foundation | C4: Orientation | D4: https://www.lfedge.org/resources/whitepapers/ | E4: 2026-09-01 | F4: 2026-09-07 | G4: 2026-09-07 | H4: 10 | I4: 10 | J4: 1 | K4: 5 | L4: Free Open Access | M4: Completed | N4: Gained complete taxonomy of LF Edge projects (Akraino, EdgeX Foundry, Fledge).
A5: CS144: Introduction to Computer Networking | B5: Stanford University | C5: Networking | D5: https://cs144.github.io/ | E5: 2026-09-08 | F5: 2026-09-22 | H5: 35 | I5: 0 | J5: 0 | L5: Free OpenCourseWare | M5: Not Started | N5: Focusing on reliable transport, sliding window flow control, and buffer management.
A6: CS6250: Software-Defined Networking | B6: Georgia Tech (OMSCS) / YouTube | C6: Networking | D6: https://www.youtube.com/playlist?list=PLAwxTw4SYaPkA_TlycMocPkWz_aQn_zXw | E6: 2026-09-15 | F6: 2026-09-29 | H6: 25 | I6: 0 | J6: 0 | L6: Free Full Lectures | M6: Not Started | N6: Essential for understanding dynamic traffic engineering and edge slicing control planes.
A7: 6.5840 / 6.824: Distributed Systems | B7: MIT CSAIL / YouTube | C7: Distributed Systems | D7: https://pdos.csail.mit.edu/6.824/ | E7: 2026-09-29 | F7: 2026-10-27 | H7: 45 | I7: 0 | J7: 0 | L7: Free CSAIL Lectures | M7: Not Started | N7: Priority #1 core course. Crucial for Raft, RPC, fault tolerance, and distributed state machine.
A8: Distributed Systems Theory & Principles | B8: University of Cambridge / YouTube | C8: Distributed Systems | D8: https://www.youtube.com/playlist?list=PLeKd45zvjcDFUEv_ohr_HdUFe97RItdyB | E8: 2026-10-06 | F8: 2026-10-27 | H8: 20 | I8: 0 | J8: 0 | L8: Free Full Course | M8: Not Started | N8: Dr. Martin Kleppmann's authoritative series on replication, partitioning, and CRDTs.
A9: Linux Containers from Scratch & Hands-on Guide | B9: Open Source / Liz Rice | C9: Virtualization | D9: https://github.com/lizrice/containers-from-scratch | E9: 2026-10-27 | F9: 2026-11-03 | H9: 14 | I9: 0 | J9: 0 | L9: Free Open Source | M9: Not Started | N9: Deep dive into Linux namespaces, cgroups v2, and overlay storage engines.
A10: LFS156x: Intro to Kubernetes on Edge with K3s | B10: The Linux Foundation / edX | C10: Cloud-Native | D10: https://www.edx.org/learn/kubernetes/the-linux-foundation-introduction-to-kubernetes-on-edge-with-k3s | E10: 2026-11-03 | F10: 2026-11-17 | H10: 15 | I10: 0 | J10: 0 | L10: Free Audit Track | M10: Not Started | N10: Practical lightweight orchestration directly tailored to edge resource constraints.
A11: Multi-Access Edge Computing (MEC) Standards | B11: ETSI Standards Committee | C11: Edge Core | D11: https://www.etsi.org/technologies/multi-access-edge-computing | E11: 2026-11-17 | F11: 2026-11-24 | H11: 15 | I11: 0 | J11: 0 | L11: Free Open Standards | M11: Not Started | N11: Mastering ETSI GS MEC 003 architecture and Application Enablement Services (Mp1/Mp2).
A12: 5G Network Architecture and Slicing | B12: EURECOM / Coursera | C12: 5G/6G MEC | D12: https://www.coursera.org/learn/5g-network-architecture | E12: 2026-11-24 | F12: 2026-12-08 | H12: 20 | I12: 0 | J12: 0 | L12: Free Audit Track | M12: Not Started | N12: Detailed breakdown of UPF edge placement, 5G Core SBA, and URLLC QoS profiles.
A13: EE364a: Convex Optimization I | B13: Stanford University / YouTube | C13: Optimization | D13: https://web.stanford.edu/class/ee364a/ | E13: 2026-12-15 | F13: 2026-12-29 | H13: 35 | I13: 0 | J13: 0 | L13: Free Book & Lectures | M13: Not Started | N13: Mathematical backbone for formulating optimal task offloading and power control in CVXPY.
A14: TinyML Specialization (CS249r Material) | B14: Harvard University Edge AI Lab | C14: Edge AI | D14: https://tinyml.seas.harvard.edu/ | E14: 2026-12-29 | F14: 2027-01-12 | H14: 30 | I14: 0 | J14: 0 | L14: Free Open Material | M14: Not Started | N14: Model quantization, pruning, and low-power on-device neural network execution.
A15: Federated Learning Frameworks & Systems | B15: Flower.ai / Cambridge | C15: Edge AI | D15: https://flower.ai/docs/framework/ | E15: 2027-01-12 | F15: 2027-01-19 | H15: 20 | I15: 0 | J15: 0 | L15: Free Open Source | M15: Not Started | N15: Decentralized model training across heterogeneous edge clients under non-IID data.
A16: EdgeCloudSim Simulation Framework | B16: Boğaziçi University | C16: Simulation | D16: https://github.com/CagataySonmez/EdgeCloudSim | E16: 2027-01-26 | F16: 2027-02-09 | H16: 20 | I16: 0 | J16: 0 | L16: Free Open Source | M16: Not Started | N16: Primary research simulation platform for capstone experimental evaluation.
A17: Writing in the Sciences & Academic Publishing | B17: Stanford Online / Coursera | C17: Research Methods | D17: https://www.coursera.org/learn/sciwrite | E17: 2027-02-09 | F17: 2027-02-23 | H17: 15 | I17: 0 | J17: 0 | L17: Free Audit Track | M17: Not Started | N17: Mastering academic manuscript structure, abstract drafting, and PhD proposal writing.

Sheet Paper Tracker
A1: RESEARCH PAPER READING & CRITICAL ANALYSIS TRACKER (100% OPEN ACCESS)
A3: Deconstruct seminal and modern literature. All papers available via direct Open Access, arXiv, or institutional repositories.
A4: Paper Title | B4: Authors | C4: Year | D4: Journal / Conference | E4: Open Access Link / DOI | F4: Thematic Domain | G4: Difficulty Tier | H4: Target Week | I4: Read? | J4: Summary Written? | K4: Research Question Identified? | L4: Methodology Category | M4: Key Limitations Identified | N4: Potential Research Gap | O4: Key Citations / Related Papers | P4: Research Reflections
A5: The Case for VM-Based Cloudlets in Mobile Computing | B5: M. Satyanarayanan, P. Bahl, R. Caceres, N. Davies | C5: 2009 | D5: IEEE Pervasive Computing | E5: https://doi.org/10.1109/MPRV.2009.82 | F5: Cloudlets / Edge Foundations | G5: Seminal Landmark | H5: Week 2 | I5: Yes | J5: Yes | K5: Yes | L5: Empirical Testbed | M5: Heavy VM provisioning latency (seconds); lack of dynamic container migration. | N5: Lightweight containerized micro-cloudlets with sub-second handoff. | O5: Satyanarayanan (2017), Bonomi (2012) | P5: Foundational concept: 1-hop wireless proximity to alleviate WAN latency.
A6: Fog Computing and Its Role in the Internet of Things | B6: F. Bonomi, R. Milito, J. Zhu, S. Addepalli | C6: 2012 | D6: ACM MCC Workshop | E6: https://doi.org/10.1145/2342509.2342513 | F6: Fog Computing | G6: Seminal Landmark | H6: Week 1 | I6: Yes | J6: Yes | K6: Yes | L6: Analytical / Conceptual | M6: Conceptual taxonomy without formal mathematical resource allocation models. | N6: Multi-tenant QoS isolation across heterogeneous fog nodes. | O6: Chiang & Zhang (2016), Buyya (2016) | P6: Introduced hierarchical fog layer between sensors and centralized cloud.
A7: Edge Computing: Vision and Challenges | B7: W. Shi, J. Cao, Q. Zhang, Y. Li, L. Xu | C7: 2016 | D7: IEEE Internet of Things Journal | E7: https://doi.org/10.1109/JIOT.2016.2579198 | F7: Edge Vision & Architecture | G7: Seminal Landmark | H7: Week 1 | I7: Yes | J7: Yes | K7: Yes | L7: Survey & Architecture | M7: Broad overview; does not benchmark specific multi-tier offloading algorithms. | N7: Edge data provenance, multi-stakeholder security, and programmability. | O7: Shi et al. (2019), Varghese et al. (2016) | P7: The most cited edge computing paper. Defined edge operating system requirements.
A8: A Survey on Mobile Edge Computing: The Communication Perspective | B8: Y. Mao, C. You, J. Zhang, K. Huang, K. B. Letaief | C8: 2017 | D8: IEEE Communications Surveys & Tutorials | E8: https://doi.org/10.1109/COMST.2017.2745201 | F8: MEC & Communication | G8: Advanced | H8: Week 12 | I8: No | J8: No | K8: No | L8: Survey & Theoretical | M8: Primarily physical and MAC layer focused; limited treatment of container orchestration. | N8: Joint optimization of wireless transmission energy and edge server compute energy. | O8: Mach & Becvar (2017), Taleb (2017) | P8: Exhaustive communication and radio resource allocation models for offloading.
A9: Communication-Efficient Learning of Deep Networks from Decentralized Data | B9: H. B. McMahan, E. Moore, D. Ramage, S. Hampson, B. A. y Arcas | C9: 2017 | D9: AISTATS (arXiv Open Access) | E9: https://arxiv.org/abs/1602.05629 | F9: Federated Learning | G9: Seminal Landmark | H9: Week 19 | I9: No | J9: No | K9: No | L9: Algorithmic & Empirical | M9: Assumes uniform communication rounds; fragile under highly non-IID and straggler clients. | N9: Adaptive client selection and asynchronous gradient aggregation at the edge. | O9: Kairouz et al. (2021), Li et al. (FedProx 2020) | P9: Introduced the FedAvg algorithm, pioneering decentralized edge learning.
A10: Edge Intelligence: Paving the Last Mile of Artificial Intelligence | B10: Z. Zhou, X. Chen, E. Li, L. Zeng, K. Luo, J. Zhang | C10: 2019 | D10: Proceedings of the IEEE (arXiv) | E10: https://arxiv.org/abs/1811.08504 | F10: Edge AI | G10: Advanced | H10: Week 17 | I10: No | J10: No | K10: No | L10: Survey & Taxonomy | M10: Lacks empirical benchmarks comparing split inference vs full local inference. | N10: Dynamic split point adaptation based on real-time wireless channel coherence time. | O10: Wang et al. (2020), Deng et al. (2020) | P10: Established clear distinction between 'AI for Edge' and 'Edge for AI'.
A11: Convergence of Edge Computing and Deep Learning: A Comprehensive Survey | B11: X. Wang, Y. Han, V. C. Leung, D. Niyato, X. Yan, X. Chen | C11: 2020 | D11: IEEE CST (arXiv Open Access) | E11: https://arxiv.org/abs/1907.08349 | F11: Edge Deep Learning | G11: Advanced | H11: Week 22 | I11: No | J11: No | K11: No | L11: Survey & Algorithmic | M11: High-level overview without source code artifacts for simulator benchmarking. | N11: Co-design of neural model compression and wireless channel state awareness. | O11: Zhou et al. (2019), Kairouz (2021) | P11: Covers deep learning inference, training, and edge-cloud collaborative pipelines.
A12: Computation Offloading in Mobile Edge Computing: A Survey | B12: S. Deng, L. Huang, J. Taheri, A. Y. Zomaya | C12: 2020 | D12: IEEE Access (Fully Open Access) | E12: https://doi.org/10.1109/ACCESS.2020.2978114 | F12: Task Offloading | G12: Advanced | H12: Week 15 | I12: No | J12: No | K12: No | L12: Survey & Mathematical | M12: Many surveyed algorithms assume static topologies; fragile under high mobility. | N12: Mobility-aware proactive task migration using deep reinforcement learning. | O12: Mao (2017), Mach (2017) | P12: Systematic taxonomy of binary vs partial offloading and scheduling metrics.
A13: Advances and Open Problems in Federated Learning | B13: P. Kairouz et al. (Google Research & 50+ Co-authors) | C13: 2021 | D13: Foundations and Trends in ML (arXiv) | E13: https://arxiv.org/abs/1912.04977 | F13: Federated Learning & Privacy | G13: Graduate | H13: Week 20 | I13: No | J13: No | K13: No | L13: Comprehensive Treatise | M13: Massive breadth makes hardware-specific edge constraints secondary focus. | N13: Joint differential privacy, secure aggregation, and resource-constrained execution. | O13: McMahan (2017), Bonawitz (2019) | P13: The definitive 200+ page handbook on federated learning open problems.
A14: A Vision of 6G Wireless Systems: Applications, Trends, Technologies | B14: W. Saad, M. Bennis, M. Chen | C14: 2020 | D14: IEEE Network (arXiv Open Access) | E14: https://arxiv.org/abs/1902.06700 | F14: 6G & Future Edge | G14: Advanced | H14: Week 14 | I14: No | J14: No | K14: No | L14: Visionary & Analytical | M14: Exploratory vision; experimental terahertz testbeds were still emergent. | N14: Integrated sensing, communication, and computation (ISCC) at cell-free edge. | O14: Latva-aho (2020), Taleb (2017) | P14: Outlines transition from connected things to connected intelligence in 6G.
A15: EdgeCloudSim: An Environment for Performance Evaluation of Edge Computing | B15: C. Sonmez, A. Ozgovde, C. Ersoy | C15: 2018 | D15: ETT (Open Access Preprint) | E15: https://doi.org/10.1002/ett.3493 | F15: Simulation & Testbeds | G15: Intermediate | H15: Week 21 | I15: No | J15: No | K15: No | L15: Simulation Framework | M15: Simplified WLAN contention model; does not emulate full packet-level 5G protocols. | N15: Integration of realistic 5G NR channel models with EdgeCloudSim broker. | O15: Calheiros (CloudSim 2011), Gupta (iFogSim 2017) | P15: Essential reading to understand EdgeCloudSim architecture before capstone.
A16: Conflict-Free Replicated Data Types | B16: M. Shapiro, N. Preguiça, C. Baquero, M. Zawirski | C16: 2011 | D16: SSS (INRIA Open Access Archive) | E16: https://inria.hal.science/inria-00555588 | F16: Distributed Consistency | G16: Seminal Landmark | H16: Week 8 | I16: No | J16: No | K16: No | L16: Theoretical & Proofs | M16: State-based CRDTs suffer from unbounded metadata growth over long disconnections. | N16: Garbage collection and delta-based CRDT optimization for low-memory edge nodes. | O16: Lamport (1978), Kleppmann (2023) | P16: Pioneered mathematically provable eventual consistency without central locking.
A17: Serverless Computing on Gaussion Edge: A Survey | B17: Y. Li, Y. Lin, Y. Wang, K. Ye, C. Xu | C17: 2022 | D17: ACM Computing Surveys (arXiv) | E17: https://arxiv.org/abs/2202.04936 | F17: Edge Serverless / FaaS | G17: Advanced | H17: Week 11 | I17: No | J17: No | K17: No | L17: Survey & Architecture | M17: Does not address hardware acceleration (Edge TPU/NPU) sharing in serverless. | N17: Predictive container pre-warming using lightweight time-series forecasters. | O17: Jonas et al. (Berkeley 2019) | P17: Surveys cold-start mitigation, function scheduling, and micro-billing at the edge.

Sheet Research Ideas
A1: PhD RESEARCH IDEA BANK & PROPOSAL FORMULATION INCUBATOR
A3: Track emergent problems, research questions, methodologies, datasets, testbeds, and target supervisors for PhD proposals.
A4: Date Logged | B4: Research Domain | C4: Problem Statement | D4: Why It Matters (Impact) | E4: Current SOTA Approaches | F4: Limitations of Current SOTA | G4: Potential Research Gap | H4: Formulated Research Question (RQ) | I4: Proposed Algorithmic Method | J4: Dataset / Simulation Testbed | K4: Primary Evaluation Metrics | L4: Key Related Papers | M4: Target PhD Supervisors & Labs | N4: Priority | O4: Status
A5: 2026-09-01 | B5: Federated Edge Intelligence | C5: Non-IID data distribution and wireless channel intermittency cause severe client drift and straggler delays in mobile edge federated learning. | D5: Enables privacy-compliant distributed learning on user devices without sending raw data to central clouds. | E5: FedAvg, FedProx, SCAFFOLD with basic heuristic client selection. | F5: Static client selection ignores dynamic radio link quality and device battery states, leading to dropped aggregation rounds. | G5: Joint optimization of radio resource allocation, adaptive local epoch count, and asynchronous gradient aggregation. | H5: RQ1: How can reinforcement learning dynamically adjust local computation epochs and transmission power to minimize FL convergence time under volatile channel conditions? | I5: Multi-Agent Deep Reinforcement Learning (MADRL) + Lyapunov Optimization | J5: Flower.ai + CRAWDAD Mobility Dataset on 10 Raspberry Pi 4 edge nodes | K5: Wall-clock convergence time (s), Energy consumption (J), Model accuracy (%), Communication overhead (MB) | L5: McMahan (2017), Kairouz (2021), Wang (2020) | M5: Prof. Schahram Dustdar (TU Wien), Prof. Tarik Taleb (Ruhr Univ / Oulu), Prof. Nirwan Ansari (NJIT) | N5: High | O5: Investigating
A6: 2026-09-05 | B6: Computation Offloading & Mobility | C6: High-velocity vehicular nodes (V2X) experience rapid handovers between roadside edge units (RSUs), causing in-flight computation offloading failures. | D6: Mission-critical autonomous driving perception models require strict sub-10ms response times. | E6: Greedy nearest-RSU offloading, simple Markov chain trajectory prediction. | F6: Fails to account for server queue backlog and handover signaling overhead during task execution. | G6: Predictive graph-based task partitioning with proactive state pre-migration across candidate roadside units. | H6: RQ2: Can spatial-temporal graph neural networks accurately forecast vehicle trajectories to proactively migrate containerized execution states with zero perceived latency? | I6: Spatial-Temporal Graph Neural Network (ST-GNN) + Deep Q-Network (DQN) | J6: Simu5G / OMNeT++ with SUMO (Simulation of Urban MObility) traffic traces | K6: Task deadline violation rate (%), Handover failure rate (%), Migration bandwidth overhead (MB), RSU energy (kWh) | L6: Mao (2017), Taleb (2017), Saad (2020) | M6: Prof. Weisong Shi (Univ of Delaware), Prof. Mahadev Satyanarayanan (CMU), Prof. Falko Dressler (TU Berlin) | N6: High | O6: Investigating
A7: 2026-09-10 | B7: Edge Serverless & Cold Starts | C7: FaaS (Function-as-a-Service) at the edge suffers from severe cold-start latency (100ms - 2s) when initializing container/Wasm runtimes on memory-constrained nodes. | D7: Serverless is the ideal programming paradigm for sporadic IoT event triggers, but cold starts violate real-time SLAs. | E7: Fixed keep-alive timeout policies, pre-warmed generic containers. | F7: Static timeouts waste precious RAM on idle edge servers or miss bursty invocation spikes. | G7: Lightweight neural time-series invocation prediction combined with WebAssembly (Wasm) micro-sandboxing. | H7: RQ3: How does sub-millisecond WebAssembly instantiation combined with LSTM-based invocation forecasting reduce tail latency in edge micro-services? | I7: Wasm Micro-runtimes (Wasmtime/WasmEdge) + Transformer-based Invocation Predictor | J7: OpenFaaS on K3s Edge Testbed with Azure Functions Public Trace 2021 | K7: P99 Cold-start latency (ms), Memory footprint (MB), Idle energy dissipation (W), Function execution throughput (req/s) | L7: Li et al. (2022), Felter (2015), Xiong (2018) | M7: Prof. Rajkumar Buyya (Univ of Melbourne), Prof. Salman Baset, Prof. Cristiana Amza (Univ of Toronto) | N7: Medium | O7: Idea
A8: 2026-09-15 | B8: Green & Sustainable Edge Computing | C8: Solar- and battery-powered edge sensor nodes experience energy harvesting fluctuations, causing sudden brownouts during heavy AI inference. | D8: Self-sustaining remote environmental monitoring and agricultural edge deployments cannot rely on stable grid power. | E8: Static duty-cycling, low-power sleep modes. | F8: Cannot dynamically trade off neural inference precision (quantization level) against current energy harvesting rates. | G8: Energy-harvesting-aware dynamic model switching and progressive early-exit deep neural networks (EE-DNNs). | H8: RQ4: What is the optimal Pareto frontier between neural model exit depth and solar energy harvesting rates to maximize multi-day sensing uptime? | I8: Convex Multi-Objective Optimization + Early-Exit MobileNet / TinyML | J8: EdgeCloudSim with Solar Irradiance Real-World Harvest Traces (NREL) | K8: Battery state of charge (%), Continuous operational lifetime (days), Inference accuracy (Top-1 %), Data loss rate (%) | L8: Zhou (2019), Boyd (EE364a), Ray (2021) | M8: Prof. Vijay Janapa Reddi (Harvard), Prof. Luca Benini (ETH Zurich / Univ of Bologna) | N8: Medium | O8: Idea

Sheet Skills Matrix
A1: EDGE COMPUTING PhD COMPETENCY & TECHNICAL SKILLS MATRIX
A3: Proficiency Scale: 0=No Knowledge | 1=Awareness | 2=Basic | 3=Working Knowledge | 4=Advanced | 5=Research Ready
A4: Skill / Competency Domain | B4: Core Category | C4: Current Level (0-5) | D4: Target Level (0-5) | E4: Gap (Target - Current) | F4: Importance for PhD (1-5) | G4: Concrete Demonstration / Artifact Required | H4: Primary Source Course / Material | I4: Practical Project Alignment | J4: Status
A5: Computer Networking (TCP/IP, Sockets) | B5: Systems & Networks | C5: 3 | D5: 5 | E5: =D5-C5 | F5: 5 | G5: Implement socket communication & latency analysis | H5: Stanford CS144 (Free) | I5: Network Latency Benchmark | J5: In Progress
A6: Software-Defined Networking (SDN) | B6: Systems & Networks | C6: 2 | D6: 4 | E6: =D6-C6 | F6: 4 | G6: Write custom OpenFlow controller rules in Mininet | H6: Georgia Tech CS6250 (Free) | I6: Mininet Edge Routing Lab | J6: Not Started
A7: Distributed Systems Principles | B7: Systems & Networks | C7: 2 | D7: 5 | E7: =D7-C7 | F7: 5 | G7: Deconstruct vector clocks and Raft consensus | H7: MIT 6.824 (Free) | I7: Raft State Machine Lab | J7: Not Started
A8: Cloud Architecture & Microservices | B8: Systems & Networks | C8: 3 | D8: 4 | E8: =D8-C8 | F8: 4 | G8: Deploy microservice mesh on container runtime | H8: UIUC Cloud Specialization (Free Audit) | I8: Multi-Tier Web Topology | J8: Not Started
A9: Internet of Things Protocols (MQTT/CoAP) | B9: Systems & Networks | C9: 3 | D9: 5 | E9: =D9-C9 | F9: 4 | G9: Benchmark MQTT QoS under network throttling | H9: Curtin Univ IoT (Free Audit) | I9: EMQX Broker Benchmark | J9: Not Started
A10: Docker & Container Internals | B10: Systems & Networks | C10: 3 | D10: 5 | E10: =D10-C10 | F10: 5 | G10: Isolate processes with Linux cgroups and namespaces | H10: Liz Rice Containers from Scratch | I10: Manual cgroup Sandbox | J10: Not Started
A11: Kubernetes / K3s Orchestration | B11: Systems & Networks | C11: 2 | D11: 5 | E11: =D11-C11 | F11: 5 | G11: Deploy multi-node K3s cluster with ingress | H11: Linux Foundation LFS156x (Free Audit) | I11: K3s Edge Node Cluster | J11: Not Started
A12: Linux Systems Programming & C/Go | B12: Systems & Networks | C12: 3 | D12: 4 | E12: =D12-C12 | F12: 4 | G12: Write multi-threaded RPC client-server in Go/C | H12: MIT 6.824 Open Labs | I12: RPC Go/Python Script | J12: Not Started
A13: Python Scientific Stack (NumPy/SciPy) | B13: AI & Optimization | C13: 4 | D13: 5 | E13: =D13-C13 | F13: 5 | G13: Vectorized data processing and statistical analysis | H13: Self / Open Research Workflows | I13: Data Analysis Scripts | J13: In Progress
A14: Edge Computing Architecture (MEC) | B14: Edge Architecture | C14: 2 | D14: 5 | E14: =D14-C14 | F14: 5 | G14: Map ETSI MEC interfaces to 5G SBA functions | H14: ETSI GS MEC 003 Open Specs | I14: MEC Taxonomy Whitepaper | J14: In Progress
A15: 5G Core & Network Slicing | B15: Edge Architecture | C15: 2 | D15: 4 | E15: =D15-C15 | F15: 5 | G15: Simulate URLLC vs eMBB slice isolation | H15: EURECOM 5G Course (Free Audit) | I15: 5G Network Slice Model | J15: Not Started
A16: 6G Architecture & V2X Concepts | B16: Edge Architecture | C16: 1 | D16: 4 | E16: =D16-C16 | F16: 4 | G16: Analyze ISAC and high-mobility V2X handovers | H16: Univ of Oulu 6G Flagship (Free) | I16: Vehicular Handover Model | J16: Not Started
... A25: Literature Review & Gap Synthesis | B25: Research & Tools | C25: 3 | D25: 5 | E25: =D25-C25 | F25: 5 | G25: Synthesize 20+ papers and write PhD Proposal | H25: Academic Open Methodology | I25: 5-Page PhD Proposal | J25: Not Started

Sheet Simulation & Tools Guide
A1: EDGE COMPUTING RESEARCH SIMULATORS, EMULATORS & TESTBEDS (100% FREE & OPEN SOURCE)
A3: Critical comparative analysis of 100% free open-source simulators, network emulators, and physical edge testbeds for PhD research.
A4: Tool / Platform | B4: Tool Category | C4: What It Simulates & Models | D4: Key Strengths & What It Is Good For | E4: Limitations & What It Cannot Model | F4: Typical Research Applications | G4: Learning Curve (1-5) | H4: PhD Value & Recommendation | I4: Official Open-Source Repository | J4: Recommended Usage Strategy
A5: EdgeCloudSim | B5: Discrete-Event Edge Simulator | C5: Edge computing environments, mobile device mobility, WLAN/WAN network delays, edge server VM processing, and task offloading policies. | D5: Extremely modular Java codebase built on CloudSim; tailored specifically for edge offloading, mobility modeling, and multi-tier queueing. | E5: Cannot perform packet-level protocol inspection; simplified wireless interference modeling compared to full network simulators. | F5: Computation offloading evaluation, edge server capacity planning, mobile handover delay assessment. | G5: 3 | H5: Essential for PhD (Top Choice) | I5: https://github.com/CagataySonmez/EdgeCloudSim | J5: Use as the primary simulation tool for your Capstone project and initial PhD proposal experiments.
A6: iFogSim / iFogSim2 | B6: Fog/Edge Discrete Simulator | C6: Hierarchical Fog-to-Cloud infrastructure, Sense-Compute-Actuate loops, energy consumption, and distributed dataflow DAGs. | D6: Excellent built-in energy consumption models and stream processing DAG placement algorithms across IoT/Fog nodes. | E6: Mobility modeling is relatively primitive in basic version; scalability drops under massive dynamic mobile node counts. | F6: IoT stream analytics placement, energy-aware fog resource scheduling, smart city telemetry. | G6: 3 | H6: Highly Recommended | I6: https://github.com/Cloudslab/iFogSim | J6: Use when research explicitly focuses on hierarchical energy modeling and multi-operator IoT stream processing.
A7: CloudSim / CloudSim Plus | B7: Cloud Infrastructure Simulator | C7: Datacenter virtualization, VM provisioning, host CPU scheduling, power consumption, and storage provisioning. | D7: The global gold-standard foundation for cloud computing research; battle-tested with hundreds of extension modules. | E7: Pure cloud focus; lacks native models for edge device mobility, wireless channel fading, and multi-access edge handovers. | F7: Centralized cloud resource provisioning, datacenter energy optimization, VM migration algorithms. | G7: 2 | H7: Good for Baselines | I7: https://github.com/cloudsimplus/cloudsimplus | J7: Understand its architecture because EdgeCloudSim and iFogSim extend it directly.
A8: ns-3 (Network Simulator 3) | B8: Packet-Level Network Simulator | C8: Discrete-event packet-level network protocols (TCP/IP, 802.11 Wi-Fi, 4G LTE, 5G NR, routing, MAC layer queues). | D8: Extreme realism at physical and link layers; authoritative standard for telecommunications research. | E8: High learning curve (C++/Python); computationally heavy when simulating complex application compute workloads for thousands of nodes. | F8: Joint wireless channel and MEC scheduling, 5G NR Beamforming, URLLC packet latency validation. | G8: 5 | H8: Essential for Comms PhD | I8: https://www.nsnam.org/ | J8: Essential if your PhD focus is communication-centric MEC; pair with Simu5G for cellular edge.
A9: Simu5G / SimuLTE (OMNeT++) | B9: 5G Cellular MEC Simulator | C9: 5G New Radio (NR) User Plane, gNodeB base stations, 5G Core (UPF) MEC data planes, and V2X sidelink communication. | D9: Unmatched accuracy for 5G cellular MEC integration, network slicing QoS, and vehicular communication (V2X). | E9: Requires OMNeT++ IDE environment; steep learning curve for non-telecommunications engineers. | F9: 5G MEC UPF placement, vehicular edge computing, URLLC latency bounds. | G9: 4 | H9: Highly Recommended (5G/6G) | I9: https://simu5g.org/ | J9: Top recommendation if your PhD proposal focuses on 5G/6G cellular edge or autonomous vehicles.
A10: Mininet / Mininet-WiFi | B10: Network Emulation Framework | C10: Software-defined networking (SDN), OpenFlow switches, Linux network namespaces, and emulated Wi-Fi access points. | D10: Runs real unmodified Linux kernel network stacks and real application binaries; interacts with real SDN controllers (ONOS, Ryu). | E10: Limited to a single machine's resource limits; cannot simulate millions of nodes faster than real-time. | F10: SDN-enabled edge traffic routing, dynamic bandwidth throttling, real-world protocol testing. | G10: 3 | H10: Highly Recommended (SDN) | I10: http://mininet.org/ | J10: Ideal for prototyping custom SDN routing controllers and validating MQTT under network throttling.
A11: K3s / KubeEdge Testbed | B11: Real-World Edge Orchestration | C11: Production-grade lightweight Kubernetes clusters running on real hardware (Raspberry Pis, Jetson Nano, x86 mini-PCs). | D11: 100% realistic real-world deployment; zero simulation bias. Uncovers OS, kernel, and real hardware bottlenecks. | E11: Hardware cost required; experiments take physical clock time to run; difficult to test 10,000 nodes without cloud emulators. | F11: Validating PhD algorithms in real physical testbeds; final paper empirical validation section. | G11: 3 | H11: Essential for Systems PhD | I11: https://k3s.io/ | J11: Build a 2-3 node testbed during Months 3-5 to provide bulletproof empirical credibility for your PhD application.

Sheet Recommended Path
A1: CURATED PhD LEARNING PATHWAY — 100% STRICTLY FREE OPEN-ACCESS
A3: Zero Paywalls. Eliminates cognitive overload. Strictly separates non-negotiable core mastery from specialized optional topics.
A4: Selection Tier | B4: Thematic Focus | C4: Resource Title | D4: Institution / Platform | E4: Access / Cost | F4: Est. Hours | G4: Why This Resource is Included | H4: Expected Key Milestone
A5: Tier 1: Must Take | B5: Edge Fundamentals | C5: Linux Foundation: Intro to Edge Computing & Shi (2016) Vision Paper | D5: LF Edge / IEEE | E5: 100% Free Open Access | F5: 16 | G5: Establishes standard industrial and academic taxonomy without vendor bias. | H5: Taxonomy Memorandum
A6: Tier 1: Must Take | B6: Networking Depth | C6: Stanford CS144: Introduction to Computer Networking | D6: Stanford University | E6: 100% Free OpenCourseWare | F6: 35 | G6: Rigorous graduate-level networking foundation (TCP/IP, latency, buffers). | H6: Network Latency Lab
A7: Tier 1: Must Take | B7: Distributed Systems | C7: MIT 6.5840 / 6.824: Distributed Systems (Prof. Robert Morris) | D7: MIT CSAIL / YouTube | E7: 100% Free Full Materials | F7: 45 | G7: Non-negotiable bedrock for all edge systems research (Raft, RPC, consistency). | H7: Raft Consensus Lab
A8: Tier 1: Must Take | B8: Cloud-Native Orchestration | C8: LFS156x: Intro to Kubernetes on Edge with K3s | D8: Linux Foundation / edX | E8: 100% Free Audit Track | F8: 15 | G8: Directly addresses container orchestration on resource-constrained edge hardware. | H8: K3s Cluster Deployment
A9: Tier 1: Must Take | B9: MEC Standards | C9: ETSI GS MEC 003 Architectural Specification & Whitepapers | D9: ETSI Standards | E9: 100% Free Open Standards | F9: 15 | G9: Authoritative telecommunications framework governing multi-access edge computing. | H9: MEC Architecture Map
A10: Tier 1: Must Take | B10: Optimization Theory | C10: Stanford EE364a: Convex Optimization I (Prof. Stephen Boyd) | D10: Stanford University | E10: 100% Free Book & Lectures | F10: 35 | G10: Mathematical formulation tool for all computation offloading & resource allocation. | H10: CVXPY Offloading Model
A11: Tier 1: Must Take | B11: Edge AI & TinyML | C11: Harvard CS249r: TinyML Course Materials & Textbook | D11: Harvard University Edge AI | E11: 100% Free Open Materials | F11: 30 | G11: Teaches quantization, pruning, and low-power embedded neural inference. | H11: Quantized Edge AI Model
A12: Tier 1: Must Take | B12: Federated Intelligence | C12: Flower.ai Framework Tutorials & McMahan FedAvg Paper | D12: Flower.ai / Cambridge | E12: 100% Free Open Source | F12: 20 | G12: Hands-on implementation of decentralized privacy-preserving edge machine learning. | H12: Federated Learning Code
A13: Tier 1: Must Take | B13: Simulation Platform | C13: EdgeCloudSim: Environment for Performance Evaluation | D13: Boğaziçi University | E13: 100% Free Open Source | F13: 20 | G13: Primary research simulator for generating empirical data for PhD proposal. | H13: Capstone Simulation
A14: Tier 1: Must Take | B14: Research Methodology | C14: Writing in the Sciences (Dr. Kristin Sainani) | D14: Stanford Online / Coursera | E14: 100% Free Audit Track | F14: 15 | G14: Essential guidance on paper structuring, abstract drafting, and proposal defense. | H14: PhD Research Proposal
A15: Tier 2: Strongly Recommended | B15: SDN Networking | C15: Georgia Tech CS6250: Software-Defined Networking | D15: Georgia Tech / YouTube | E15: 100% Free Full Lectures | F15: 25 | G15: Dynamic network slicing and programmable control plane mastery. | H15: Mininet Controller
A16: Tier 2: Strongly Recommended | B16: Data Systems | C16: Distributed Systems Theory Course (Dr. Martin Kleppmann) | D16: Cambridge / YouTube | E16: 100% Free Full Course | F16: 20 | G16: Superb coverage of replication, partitioning, transactions, and CRDTs. | H16: CRDT State Sync Script
... A24: Tier 4: Reference Only | B24: FL Treatise | C24: Advances and Open Problems in Federated Learning (arXiv) | D24: Google Research | E24: 100% Free Open Access | F24: 0 | G24: Exhaustive 200-page survey to reference for open problems in privacy. | H24: Zotero Library Item

Sheet PhD Readiness Assessment
A1: PhD APPLICANT READINESS ASSESSMENT & RUBRIC EVALUATION
A3: Scoring Rubric: 0=Not Ready | 1=Basic Awareness | 2=Competent B.Eng. | 3=Strong Master's Level | 4=Research Ready (PhD Applicant)
A4: Competency Area | B4: Specific PhD Readiness Assessment Criterion | C4: Self-Score (0-4) | D4: Required Evidence & Demonstration | E4: Evaluation Guidance (What 'Research Ready' Looks Like) | F4: Status | G4: Verification Notes & Action Items
A5: Edge Foundations | B5: Explain Edge Computing clearly and why it is physically and economically necessary | C5: 4 | D5: 1-Page Taxonomy Memorandum | E5: Can articulate latency speed-of-light limits, backhaul bandwidth bottlenecks, and data privacy drivers without vague buzzwords. | F5: Achieved | G5: Fully articulated in Month 1
A6: Edge Foundations | B6: Differentiate Edge vs Cloud vs Fog vs Cloudlets vs MEC with precise architectural distinctions | C6: 4 | D6: Comparative Taxonomy Architecture Map | E6: Can explain standard bodies (ETSI MEC vs OpenFog vs CNCF) and exact network tier placements. | F6: Achieved | G6: Diagrammed in Month 1
A7: Edge Foundations | B7: Explain device-edge-cloud hierarchical interaction and resource discovery models | C7: 3 | D7: Multi-tier Dataflow Simulation Script | E7: Can describe how edge brokers register resources, handle DNS/IP routing, and offload to cloud. | F7: In Progress | G7: Refining in Month 3
A8: Systems & Consensus | B8: Explain distributed consensus (Paxos, Raft) and why it is challenging across edge nodes | C8: 3 | D8: Raft State Machine Implementation | E8: Can explain why network partitions and high round-trip times complicate quorum formation in edge clusters. | F8: In Progress | G8: Completing in Month 2
A9: Cloud-Native Systems | B9: Explain container orchestration (K8s/K3s) and edge worker autonomy during disconnection | C9: 3 | D9: 2-Node K3s Cluster Deployment | E9: Can explain how KubeEdge and K3s handle offline node operation and reconcile desired vs actual state. | F9: Not Started | G9: Scheduled for Month 3
A10: Telecommunications | B10: Explain 5G/6G Core, Service-Based Architecture (SBA), UPF placement, and Network Slicing | C10: 3 | D10: 5G Slicing & UPF Case Study | E10: Can explain how 3GPP User Plane Functions integrate with ETSI MEC platforms to guarantee URLLC latency. | F10: Not Started | G10: Scheduled for Month 4
A11: Optimization Theory | B11: Formulate computation offloading and resource allocation mathematically (Convex/LP/DRL) | C11: 3 | D11: CVXPY Offloading Code & Proof | E11: Can formulate multi-variable cost functions (energy + delay), identify constraints, and prove NP-hardness. | F11: Not Started | G11: Scheduled for Month 4
A12: Edge AI / Intelligence | B12: Explain Edge AI trade-offs, model compression (quantization/pruning), and embedded inference | C12: 3 | D12: INT8 Quantized Neural Model Report | E12: Can explain post-training quantization vs quantization-aware training and memory bandwidth limits on NPUs. | F12: Not Started | G12: Scheduled for Month 5
A13: Federated Learning | B13: Explain Federated Learning (FedAvg), client drift under non-IID data, and communication costs | C13: 3 | D13: Flower.ai 5-Node FL Simulation | E13: Can explain why heterogeneous client updates diverge and how gradient compression / FedProx mitigates drift. | F13: Not Started | G13: Scheduled for Month 5
A14: Edge Security & Privacy | B14: Explain Edge attack surfaces, Trusted Execution Environments (TEEs), and Differential Privacy | C14: 3 | D14: Differential Privacy Python Lab | E14: Can explain ARM TrustZone enclaves, secure aggregation in FL, and epsilon-delta privacy budgets. | F14: Not Started | G14: Scheduled for Month 5
A15: Simulation Competence | B15: Set up and execute discrete-event simulations in EdgeCloudSim / ns-3 with realistic parameters | C15: 3 | D15: EdgeCloudSim Benchmark Run Data | E15: Can configure mobility models, network delay distributions, CPU task loads, and extract statistical results. | F15: Not Started | G15: Scheduled for Month 6
A16: Research Methodology | B16: Read top-tier Edge Computing papers and rapidly extract RQs, methodologies, and limitations | C16: 4 | D16: 15+ Completed Paper Reviews in Tracker | E16: Can critically dissect IEEE/ACM papers, identify unstated assumptions, and spot methodological flaws. | F16: In Progress | G16: Ongoing weekly task
... A20: Academic Presentation | B20: Defend proposed research methodology and articulate academic contributions clearly | C20: 3 | D20: Recorded Mock Proposal Presentation | E20: Can confidently answer probing questions regarding scalability, feasibility, and baseline comparison. | F20: Not Started | G20: Scheduled for Month 6
A21: OVERALL PhD READINESS COMPOSITE INDEX (Average Score) | C21: =AVERAGE(C5:C20) | D21: =IF(C21>=3.5, "EXCEPTIONAL — Fully Research Ready for Top-Tier PhD", IF(C21>=2.8, "STRONG — Highly Competitive PhD Applicant with Strong Foundations", "DEVELOPING — Continue Progressing Through Curriculum"))

Sheet HK Supervisor Intelligence
A1: HONG KONG PhD SUPERVISOR INTELLIGENCE (8 TARGET UNIVERSITIES)
A3: University | B3: Professor | C3: Department | D3: Position | E3: Research Group | F3: Primary Research Focus | G3: Priority Tier | H3: Alignment Score (%) | I3: Recruitment Status | J3: Recruitment Evidence | K3: Seminal / Key Publication | L3: Recent Breakthrough Paper | M3: Active Projects / Grants | N3: Simulators & Testbeds | O3: Mapped Curriculum Weeks | P3: Official Profile URL | Q3: Application Action / Status
A4: The Hong Kong Polytechnic University | B4: Prof. Jiannong Cao | C4: Department of Computing (COMP) | D4: Dean of Graduate School, Otto Poon Charitable Foundation Professor in Data Science, Chair Professor of Distributed and Mobile Computing | E4: Internet and Mobile Computing Laboratory (IMCL) | F4: Edge Computing, Edge AI, Distributed Systems | G4: Tier 1 | H4: 96 | I4: CONFIRMED_ACTIVE | J4: We are seeking highly motivated PhD students and Postdocs with strong backgrounds in Computer Science, Computer Engineering, or Mathematics to join IMCL for Fall 2027. Full scholarships (HKPFS and PolyU Presidential Fellowship) available. (2026-06-15) | K4: Edge Mesh: A New Paradigm to Enable Distributed Intelligence in Internet of Things | L4: EdgeShard: Efficient LLM Inference via Collaborative Edge Computing | M4: RGC CRF: Collaborative Edge Computing Architecture for Smart Cities; Edge Intelligence Framework for Real-time Video Stream Analytics | N4: EdgeCloudSim, ns-3, Mininet, OMNeT++, 50-node Raspberry Pi 4 Edge Cluster | O4: Weeks 1, 5, 6, 7 | P4: https://www.polyu.edu.hk/comp/people/academic-staff/prof-cao-jiannong/ | Q4: Identified — Ready for Outreach
A5: The Hong Kong University of Science and Technology | B5: Prof. Wei Wang | C5: Department of Computer Science and Engineering (CSE) | D5: Associate Professor | E5: System Networking Lab (SING) | F5: Distributed Machine Learning, Edge Intelligence, Cloud-Edge Systems | G5: Tier 1 | H5: 96 | I5: CONFIRMED_ACTIVE | J5: Multiple PhD openings available each year. If you are interested in building real computer systems for distributed AI and edge computing, email me with your CV, transcripts, and a brief research statement. HKPFS candidates are strongly encouraged. (2026-06-30) | K5: Enabling Cost-Effective, SLO-Aware Machine Learning Inference Serving on Public Cloud | L5: Enabling Cost-Effective, SLO-Aware Machine Learning Inference Serving on Public Cloud | M5: Efficient Distributed Training on Heterogeneous Cloud-Edge GPU Clusters; Communication-Efficient Federated Learning Frameworks for IoT | N5: PyTorch Distributed, Flower.ai, Horovod, 128-GPU High Performance Cluster | O5: Weeks 5, 9, 10, 11 | P5: https://cse.hkust.edu.hk/admin/people/faculty/profile/weiwa | Q5: Identified — Ready for Outreach
A6: The University of Hong Kong | B6: Prof. Chuan Wu | C6: Department of Computer Science (CS) | D6: Professor | E6: Systems Research Group | F6: Cloud and Edge Computing, Distributed Machine Learning Systems, Resource Scheduling | G6: Tier 1 | H6: 96 | I6: CONFIRMED_ACTIVE | J6: I am looking for self-motivated PhD students with strong programming and mathematical skills to work on distributed systems, edge computing, and AI systems. High-achieving students will be nominated for HKU Presidential PhD Scholarship and HKPFS. (2026-07-15) | K6: DL2: A Deep Learning-Driven Scheduler for Deep Learning Clusters | L6: Task Placement and Resource Allocation for Edge Machine Learning: A GNN-Based Multi-Agent Reinforcement Learning Paradigm | M6: RGC GRF: Efficient Inference Serving of Foundation Models over Edge Networks; Pipelined Collaborative Learning across Heterogeneous Mobile Edge Devices | N6: PyTorch Distributed, Ray, Deepspeed, HKU GPU Cluster (Nvidia A100/H100) | O6: Weeks 5, 6, 7, 11 | P6: https://www.cs.hku.hk/people/academic-staff/cwu | Q6: Identified — Ready for Outreach
A7: The Hong Kong Polytechnic University | B7: Prof. Song Guo | C7: Department of Computing (COMP) | D7: Chair Professor of Distributed and Mobile Computing, IEEE Fellow, Member of European Academy of Sciences | E7: Pervasive AI & Cloud-Edge Systems Group | F7: Edge Intelligence, Mobile Edge Computing, Federated Learning | G7: Tier 1 | H7: 95 | I7: CONFIRMED_ACTIVE | J7: Looking for self-driven PhD students with strong coding (Python/C++) and mathematical background to work on Edge AI, Federated Learning, and Distributed Computing for 2027 entry. HKPFS applicants warmly welcomed. (2026-07-10) | K7: A Learning-Based Incentive Mechanism for Federated Learning | L7: Wireless Powered Mobile Edge Computing Networks: A Survey | M7: RGC Theme-based Research Scheme: Trustworthy Edge Intelligence; Communication-Efficient Federated Learning across Non-IID Mobile Clients | N7: Flower.ai, FedML, EdgeCloudSim, SimPy, 32-node GPU/Edge NPU Testbed (Jetson AGX/Xavier) | O7: Weeks 8, 12, 16, 17 | P7: https://www.polyu.edu.hk/comp/people/academic-staff/prof-guo-song/ | Q7: Identified — Ready for Outreach
A8: The Hong Kong University of Science and Technology | B8: Prof. Lin Wang | C8: Department of Computer Science and Engineering (CSE) | D8: Associate Professor | E8: Edge Computing Systems Laboratory | F8: Edge Computing Systems, Serverless Edge Computing, Cloud-Edge Resource Allocation | G8: Tier 1 | H8: 95 | I8: CONFIRMED_ACTIVE | J8: I am seeking PhD students interested in Edge Computing, Serverless Systems, and Cloud-Native Technologies for 2027 entry. Successful candidates will be supported by HKPFS or HKUST Postgraduate Studentships. (2026-07-01) | K8: N/A | L8: N/A | M8: WebAssembly Runtimes for Latency-Critical Edge Serverless; Predictive Pre-warming of Edge Containers using Temporal Machine Learning | N8: SimPy, CloudSim Plus, K3s / OpenFaaS Edge Testbed | O8: Weeks 9, 10, 11, 12 | P8: https://cse.hkust.edu.hk/admin/people/faculty/profile/linwang | Q8: Identified — Ready for Outreach
A9: City University of Hong Kong | B9: Prof. Jianping Wang | C9: Department of Computer Science (CS) | D9: Professor, IEEE Fellow | E9: Future Networking Laboratory | F9: Edge Computing in Connected Vehicles, Autonomous Driving Systems, Cloud Computing | G9: Tier 1 | H9: 95 | I9: CONFIRMED_ACTIVE | J9: Recruiting PhD students for 2027 entry in Connected Autonomous Vehicles, Edge Computing, and Cloud Networks. CityU Presidential PhD Scholarship (HK$331,200/yr) and HKPFS available for top applicants. (2026-07-05) | K9: AoI-Aware User Service Satisfaction Enhancement in Digital Twin-Empowered Edge Computing | L9: AoI-Aware User Service Satisfaction Enhancement in Digital Twin-Empowered Edge Computing | M9: RGC Theme-based Research Scheme: Autonomous Driving in Dense Urban Environments; Proactive Task Migration for High-Speed Connected Vehicles | N9: SUMO, Simu5G, OMNeT++, CARLA, Autonomous Driving Scale-Model Testbed | O9: Weeks 13, 14, 15, 16 | P9: https://www.cs.cityu.edu.hk/people/academic-staff/jianwang | Q9: Identified — Ready for Outreach
A10: The Chinese University of Hong Kong | B10: Prof. Minghua Chen | C10: Department of Information Engineering (IE) | D10: Professor, IEEE Fellow, ACM Distinguished Member | E10: Advanced Networking and System Research Laboratory (ANSRLab) | F10: Online Optimization, Edge Computing Resource Allocation, Green & Sustainable Edge | G10: Tier 1 | H10: 93 | I10: STRONG_EVIDENCE | J10: I am constantly looking for excellent PhD students with strong passion and solid mathematical/systems background. Please submit your application through CUHK Graduate School and mention my name. (2026-05-20) | K10: Markov Approximation for Combinatorial Network Optimization | L10: Unsupervised Learning for Solving AC Optimal Power Flows: Design, Analysis, and Experiment | M10: RGC GRF: Online Algorithms for Carbon-Aware Edge Intelligence; Joint Energy Harvesting and Computation Scheduling for Remote IoT Networks | N10: CVXPY, MATLAB, SimPy, Custom Python Optimization Simulator Suite | O10: Weeks 13, 14, 15, 16 | P10: https://www.ie.cuhk.edu.hk/people/minghua.shtml | Q10: Identified — Ready for Outreach
A11: The University of Hong Kong | B11: Prof. Heming Cui | C11: Department of Computer Science (CS) | D11: Associate Professor | E11: Systems Research Group | F11: Distributed Systems, Concurrency, Fault Tolerance | G11: Tier 1 | H11: 93 | I11: STRONG_EVIDENCE | J11: I am seeking PhD students passionate about building reliable, high-performance distributed systems. Students with strong C/C++/Go programming skills and interest in SOSP/OSDI publications are encouraged to apply. (2026-05-30) | K11: vPipe: A Virtualized Acceleration System for Achieving Efficient and Scalable Pipeline Parallel DNN Training | L11: vPipe: A Virtualized Acceleration System for Achieving Efficient and Scalable Pipeline Parallel DNN Training | M11: Fault-Tolerant Distributed Protocols for Unreliable Edge Networks; Formal Verification of Distributed Concurrency in Edge OS | N11: Jepsen Distributed Testing Framework, Mininet, Distributed Linux Kernel Testbed | O11: Weeks 5, 6, 7, 8 | P11: https://www.cs.hku.hk/people/academic-staff/heming | Q11: Identified — Ready for Outreach
A12: The Chinese University of Hong Kong | B12: Prof. John C.S. Lui | C12: Department of Computer Science and Engineering (CSE) | D12: Choh-Ming Li Professor of Computer Science and Engineering, ACM Fellow, IEEE Fellow | E12: Advanced Networking and System Research Laboratory | F12: Network Systems, Edge Caching, Reinforcement Learning in Networking | G12: Tier 1 | H12: 92 | I12: STRONG_EVIDENCE | J12: Seeking talented, self-motivated graduate students wishing to pursue PhD degrees in networked systems, edge intelligence, and reinforcement learning. Prospective HKPFS applicants should contact me directly. (2026-06-01) | K12: Task Co-Offloading for D2D-Assisted Mobile Edge Computing in Industrial Internet of Things | L12: Task Co-Offloading for D2D-Assisted Mobile Edge Computing in Industrial Internet of Things | M12: Multi-Agent Reinforcement Learning for Dynamic Edge Spectrum Sharing; Security and Robustness of Cooperative Edge Caching Systems | N12: ns-3, Simu5G, PyTorch, Campus Wide-Area Testbed | O12: Weeks 2, 3, 13, 14 | P12: https://www.cse.cuhk.edu.hk/people/faculty/john-c-s-lui/ | Q12: Identified — Ready for Outreach
A13: Hong Kong Baptist University | B13: Prof. Xiaowen Chu | C13: Department of Computer Science (COMP) | D13: Professor | E13: High Performance Computing and Systems Laboratory | F13: GPU Computing, Deep Learning Systems, Edge AI Inference | G13: Tier 1 | H13: 92 | I13: CONFIRMED_ACTIVE | J13: Looking for highly motivated PhD students with strong coding skills in C/C++/Python and knowledge of computer architecture to work on GPU computing and Edge AI. Supported by HKBU VC Fellowship and HKPFS. (2026-06-25) | K13: Resource-Efficient Collaborative Edge Transformer Inference With Hybrid Model Parallelism | L13: Resource-Efficient Collaborative Edge Transformer Inference With Hybrid Model Parallelism | M13: Benchmarking and Acceleration of Large Language Models on Mobile Edge GPUs; Energy-Efficient Neural Network Deployment on Embedded NPUs | N13: Nsight Compute, TensorRT, TVM, PyTorch, GPU Cluster with 64x Nvidia RTX/A100 | O13: Weeks 9, 17, 18, 19 | P13: https://www.comp.hkbu.edu.hk/v1/?page=profile&id=chxw | Q13: Identified — Ready for Outreach
A14: Lingnan University | B14: Prof. Sam Kwong | C14: School of Data Science | D14: Associate Vice-President (Strategic Research), Chair Professor of Computational Intelligence, IEEE Fellow | E14: Computational Intelligence and Data Science Laboratory | F14: Computational Intelligence, Video Compression for Edge Devices, Evolutionary Computation | G14: Tier 2 | H14: 85 | I14: STRONG_EVIDENCE | J14: Seeking outstanding PhD candidates in Data Science, Computational Intelligence, and Edge Video Processing. Full financial support through Lingnan Postgraduate Studentship (HK$18,480/mo) and HKPFS (HK$27,600/mo). (2026-06-10) | K14: Matrix-Based Evolutionary Computation | L14: Matrix-Based Evolutionary Computation | M14: Low-Complexity Intelligent Video Analytics for Smart IoT Sensors; Evolutionary Neural Architecture Search for Edge Devices | N14: VVC Reference Software (VTM), PyTorch, MATLAB, High-Performance Computing Cluster at Lingnan School of Data Science | O14: Weeks 4, 16, 17, 18 | P14: https://www.ln.edu.hk/sds/people/faculty/prof-kwong-tak-wu-sam | Q14: Identified — Ready for Outreach
A15: The Education University of Hong Kong | B15: Prof. Philip L.H. Yu | C15: Department of Mathematics and Information Technology (MIT) | D15: Head of Department and Professor | E15: Artificial Intelligence and Digital Competency Education Centre | F15: Statistical Machine Learning, Distributed IoT Stream Analytics, Anomaly Detection | G15: Tier 3 | H15: 78 | I15: POSSIBLE | J15: Welcomes applications from qualified candidates for PhD study in Mathematics, Information Technology, and Applied Machine Learning. Studentships provided through EdUHK Graduate School. (2026-05-15) | K15: Exploring the application of ChatGPT in ESL/EFL education and related research issues: a systematic review of empirical studies | L15: Exploring the application of ChatGPT in ESL/EFL education and related research issues: a systematic review of empirical studies | M15: Real-Time Anomaly Detection on Distributed Environmental Edge Sensors; Statistical Quality Control in High-Frequency IoT Sensor Networks | N15: R, Python, SimPy, Campus-wide IoT Sensing Testbed | O15: Weeks 4, 15, 21 | P15: https://www.eduhk.hk/mit/people/academic-staff/yu-leung-ho-philip | Q15: Identified — Ready for Outreach

Sheet HK Scholarships & Deadlines
A1: HONG KONG PhD SCHOLARSHIPS & DOCTORAL FUNDING SCHEMES
A3: University | B3: Scholarship Scheme Name | C3: Target PhD Program | D3: Application Deadline | E3: Days Remaining | F3: Annual Funding (HKD) | G3: Monthly Living Allowance | H3: Tuition Coverage | I3: Duration | J3: Dependent Support | K3: Supervisor Requirement | L3: Official Portal URL | M3: Verification Source
A4: All 8 Hong Kong Universities (RGC Scheme) | B4: Hong Kong PhD Fellowship Scheme (HKPFS) | C4: All PhD Programs across 8 UGC-funded Institutions | D4: 2026-12-01 12:00:00 HKT (Strict Initial Application to RGC) | E4: 59 days | F4: HK$331,200 / year (approx. US$42,460) | G4: Monthly stipend of HK$27,600 | H4: Varies by host university (fully waived or subsidized by university top-ups) | I4: Up to 3 years (4 years for 4-year PhD programs via university top-up) | J4: Not provided directly by RGC (dependent visas permitted by HK ImmD, but no explicit stipend allowance) | K4: Preliminary supervisor contact recommended before university submission; required at institutional stage | L4: https://cerg1.ugc.edu.hk/hkpfs/index.html | M4: Research Grants Council (RGC) of Hong Kong
A5: The University of Hong Kong | B5: HKU Presidential PhD Scholarship (HKU-PS) | C5: PhD in Computer Science / Electrical & Electronic Engineering | D5: 2026-12-01 23:59:59 HKT | E5: 59 days | F5: Up to HK$441,400 in Year 1 (Cash award + PGS + travel subsidy) | G5: Cash award of HK$40,000 in Year 1 + monthly PGS of ~HK$18,720 to HK$27,600 | H5: Full tuition fee waiver of HK$42,100 / year | I5: Up to 4 years for 4-year PhD | J5: No explicit dependent living stipend allowance (health benefits covered on-campus for student) | K5: Strongly advised to identify and obtain preliminary agreement from target supervisor | L5: https://gradsch.hku.hk/prospective-students/fees-scholarships-and-financial-aid/hku-presidential-phd-scholarship | M5: HKU Graduate School
A6: The Hong Kong University of Science and Technology | B6: HKUST RedBird PhD Award & Postgraduate Studentship (PGS) | C6: PhD in Computer Science and Engineering / Electronic and Computer Engineering | D6: 2026-12-01 23:59:59 HKT | E6: 59 days | F6: HK$40,000 recruitment award + full annual PGS of HK$220,680 (approx HK$18,390/mo) | G6: Monthly PGS stipend of HK$18,390 (HK$27,600 if HKPFS awardee) | H6: Tuition scholarship available for HKPFS recipients (HK$42,100/yr) | I6: 4 years (standard 4-year PhD) | J6: None officially provided for dependents | K6: Highly recommended to engage prospective faculty before formal committee review | L6: https://fytgs.hkust.edu.hk/scholarships/hkust-redbird-phd-award-scheme | M6: HKUST Fok Ying Tung Graduate School
A7: The Chinese University of Hong Kong | B7: CUHK Vice-Chancellor's PhD Scholarship Scheme | C7: PhD in Information Engineering / Computer Science and Engineering | D7: 2026-12-01 23:59:59 HKT | E7: 59 days | F7: HK$40,000 - HK$80,000 award + tuition waiver + full studentship | G7: Monthly PGS of HK$18,725 or HKPFS rate of HK$27,600 | H7: Full tuition waiver of HK$42,100 / year for HKPFS recipients | I7: Normative study period (3 to 4 years) | J7: No separate dependent allowance | K7: Mandatory to list prospective supervisor; prior contact strongly recommended | L7: https://www.gs.cuhk.edu.hk/admissions/scholarships-fees/scholarships | M7: CUHK Graduate School
A8: The Hong Kong Polytechnic University | B8: PolyU Presidential PhD Fellowship Scheme (PPPFS) | C8: PhD in Computing / Electronic and Information Engineering | D8: 2026-12-01 23:59:59 HKT | E8: 59 days | F8: Annual cash award of HK$40,000 + full tuition waiver + monthly stipend | G8: Monthly stipend of HK$27,290 (or HK$27,600 for HKPFS) | H8: Full tuition waiver (HK$42,100 / year) | I8: Up to 4 years | J8: None officially provided | K8: Target supervisor must support the application for PPPFS nomination | L8: https://www.polyu.edu.hk/gs/financial-support/scholarships-and-awards/ | M8: PolyU Graduate School
A9: City University of Hong Kong | B9: CityU Presidential PhD Scholarship (CBPS) & PGS | C9: PhD in Computer Science / Electrical Engineering | D9: 2026-12-01 23:59:59 HKT | E9: 59 days | F9: Monthly scholarship of HK$27,600 (HK$331,200/yr) + travel allowance | G9: Monthly allowance of HK$27,600 | H9: Institutional research tuition grant provided | I9: Up to 4 years | J9: None officially provided | K9: Supervisor endorsement required prior to school ranking | L9: https://www.cityu.edu.hk/pg/research-degree-programmes/scholarships-financial-aid-and-fees | M9: CityU Chow Yei Ching School of Graduate Studies
A10: Hong Kong Baptist University | B10: HKBU Vice-Chancellor's PhD Fellowship Scheme | C10: PhD in Computer Science | D10: 2026-12-01 23:59:59 HKT | E10: 59 days | F10: HK$27,600 / month + tuition scholarship + research travel fund | G10: Monthly PGS stipend of ~HK$18,500 - HK$27,600 | H10: Full waiver of tuition fee for HKPFS awardees | I10: Up to 3-4 years | J10: None officially provided | K10: Strongly recommended to contact faculty advisor in advance | L10: https://gs.hkbu.edu.hk/fees-and-scholarships/scholarships | M10: HKBU Graduate School
A11: Lingnan University | B11: Lingnan Full-Time Postgraduate Studentship (PGS) & HKPFS | C11: PhD in Data Science / Computer Science | D11: 2026-12-01 23:59:59 HKT | E11: 59 days | F11: Monthly studentship of HK$18,480 (or HK$27,600 for HKPFS awardees) | G11: Monthly studentship of HK$18,480 | H11: Tuition scholarship available for top-ranked applicants | I11: Up to 3-4 years | J11: None officially provided | K11: Applicants should identify a potential supervisor from the School of Data Science | L11: https://www.ln.edu.hk/sgs/financial-support/rpg | M11: Lingnan School of Graduate Studies
A12: The Education University of Hong Kong | B12: EdUHK Research Postgraduate Studentship (RPgS) | C12: PhD in Mathematics and Information Technology / Artificial Intelligence | D12: 2026-12-01 23:59:59 HKT | E12: 59 days | F12: Monthly studentship of HK$18,200 (or HK$27,600 for HKPFS awardees) | G12: Monthly studentship of HK$18,200 | H12: Tuition waivers available for distinguished students | I12: 3 to 4 years | J12: None officially provided | K12: Supervisor alignment required during departmental vetting | L12: https://www.eduhk.hk/gradsch/index.php/prospective-students/fees-and-scholarships.html | M12: EdUHK Graduate School

Sheet HK Application Tracker
A1: 10-WEEK HONG KONG PhD APPLICATION CAMPAIGN ROADMAP
A3: Campaign Week | B3: Phase | C3: Target Date Window | D3: Milestone Goal | E3: Tangible Deliverable | F3: Target Universities | G3: Key Tasks / Action Items | H3: Priority Action | I3: Completion Criteria | J3: Status | K3: Notes & Reflection
A4: Week 1 | B4: Discovery | C4: T minus 10 Weeks | D4: Week 1: University & Supervisor Discovery | E4: Comprehensive Hong Kong 8-University Supervisor & Scholarship Directory | F4: All 8 Universities | G4: Assess all 8 target universities, identify 20-30 candidate researchers, map scholarships & deadlines. | H4: Focus on Supervisor Discovery | I4: Deliverable produced and reviewed | J4: Completed
A5: Week 2 | B5: Qualification | C5: T minus 9 Weeks | D5: Week 2: Candidate Qualification & Shortlisting | E5: Tier-1 Shortlist of 10-15 Qualified Supervisors + Scholarship Mapping | F5: All 8 Universities | G5: Filter candidates down to 10-15 top potential supervisors with matched scholarships and PhD programs. | H5: Application Submission | I5: Deliverable produced and reviewed | J5: In Progress
A6: Week 3 | B6: Deep Research | C6: T minus 8 Weeks | D6: Weeks 3-4: Deep Research & Publication Analysis | E6: Deep Technical Deconstruction Dossiers for Top 5-10 Supervisors | F6: Top 3-4 Target Institutions | G6: Analyze publication history, research trajectories, current grants, and methodologies for top 5-10 candidates. | H6: Application Submission | I6: Deliverable produced and reviewed | J6: Not Started
A7: Week 4 | B7: Deep Research | C7: T minus 7 Weeks | D7: Weeks 3-4: Methodology & Research Gap Deconstruction | E7: Research Gap & Methodology Analysis Matrix | F7: Top 3-4 Target Institutions | G7: Identify unaddressed research gaps, simulators used, and active project extensions. | H7: Application Submission | I7: Deliverable produced and reviewed | J7: Not Started
A8: Week 5 | B8: Alignment | C8: T minus 6 Weeks | D8: Weeks 5-6: Research Alignment & Question Formulation | E8: Supervisor-Aligned Research Questions & Initial Outreach Email Drafts | F8: Top 3-4 Target Institutions | G8: Formulate 2-3 specific Research Questions (RQs) aligned with each priority supervisor. | H8: Outreach Preparation | I8: Deliverable produced and reviewed | J8: Not Started
A9: Week 6 | B9: Alignment | C9: T minus 5 Weeks | D9: Weeks 5-6: Personalized Supervisor Outreach | E9: Supervisor Outreach Sent & Responses Logged | F9: Top 3-4 Target Institutions | G9: Send tailored outreach emails demonstrating genuine familiarity with their recent publications. | H9: Outreach Preparation | I9: Deliverable produced and reviewed | J9: Not Started
A10: Week 7 | B10: Application Preparation | C10: T minus 4 Weeks | D10: Weeks 7-8: Research Proposal & Application Materials | E10: Polished PhD Research Proposal + Tailored Academic CV + SOP Draft | F10: Top 3-4 Target Institutions | G10: Draft 5-page PhD research proposal, tailored CV, statement of purpose, and arrange reference letters. | H10: Application Submission | I10: Deliverable produced and reviewed | J10: Not Started
A11: Week 8 | B11: Application Preparation | C11: T minus 3 Weeks | D11: Weeks 7-8: Portal Setup & Transcript Verification | E11: All University Portal Profiles Initialized & Required Documents Uploaded | F11: Top 3-4 Target Institutions | G11: Create accounts on RGC HKPFS portal and individual university graduate admissions portals. | H11: Application Submission | I11: Deliverable produced and reviewed | J11: Not Started
A12: Week 9 | B12: Final Review | C12: T minus 2 Weeks | D12: Week 9: Final Compliance Review & Quality Audit | E12: Pre-Submission Quality Audit & Final Proposal Proofing Complete | F12: Top 3-4 Target Institutions | G12: Audit eligibility, supervisor pre-approval status, scholarship requirements, and deadline verifications. | H12: Application Submission | I12: Deliverable produced and reviewed | J12: Not Started
A13: Week 10 | B13: Submission | C13: T minus 1 Weeks | D13: Week 10: Formal Application Submission | E13: HKPFS Reference Number Obtained & University Applications Submitted | F13: Top 3-4 Target Institutions | G13: Submit RGC HKPFS application ahead of Dec 1 noon deadline and finalize institutional submissions. | H13: Application Submission | I13: Deliverable produced and reviewed | J13: Not Started

Sheet Country Intelligence
A1: GLOBAL PhD FUNDING & COUNTRY RESEARCH ECOSYSTEMS
A3: Country | B3: Code | C3: Primary Funding Vehicle | D3: Universities | E3: Vetted Supervisors | F3: Key Deadline | G3: Dependant Visa Policy | H3: Status
A4: United Kingdom | B4: UK | C4: UKRI / EPSRC Doctoral Studentships & University Doctoral Scholarships | D4: 8 | E4: 9 | F4: 2026-12-15 | G4: International postgraduate research (PhD/Doctoral) students ... | H4: Active Campaign
A5: Japan | B5: JP | C5: MEXT Government Doctoral Scholarship, JSPS Research Fellowships & University Fellowships | D5: 8 | E5: 8 | F5: 2026-11-30 | G5: International doctoral students holding a College Student (R... | H5: Active Campaign
A6: Germany | B6: DE | C6: TV-L E13 Salaried Research Associate Positions (100%/75%), DAAD Grants & DFG RTGs | D6: 8 | E6: 8 | F6: 2026-12-01 | G6: Dependants (spouse and minor children) are eligible for fami... | H6: Active Campaign
A7: United States | B7: US | C7: Full Graduate Research Assistantships (100% Tuition Waiver + $30k-$48k Stipend) | D7: 8 | E7: 8 | F7: 2026-12-15 | G7: Spouses and unmarried minor children of F-1/J-1 doctoral stu... | H7: Active Campaign
A8: Canada | B8: CA | C8: Vanier CGS ($50,000/yr), NSERC Fellowships & Departmental Guaranteed PhD Funding Packages ($25k-$35k/yr) | D8: 8 | E8: 8 | F8: 2026-12-15 | G8: Spouses/common-law partners of full-time doctoral (PhD) stud... | H8: Active Campaign
A9: Sweden | B9: SE | C9: Fully Salaried Doctoral Employment (~31,000-35,000 SEK/month, free tuition, social benefits) & WASP Fellowships | D9: 8 | E9: 9 | F9: 2026-12-01 | G9: Doctoral positions in Sweden are classified as salaried empl... | H9: Active Campaign
A10: Hong Kong | B10: HK | C10: Hong Kong PhD Fellowship Scheme (HKPFS HK$331,200/yr + travel allowance) & University Postgraduate Studentships | D10: 8 | E10: 12 | F10: 2026-12-01 | G10: Full-time doctoral students in Hong Kong may sponsor legal s... | H10: Active Campaign

Sheet Global Supervisor Directory
A1: GLOBAL PhD SUPERVISOR DIRECTORY — EDGE COMPUTING & DISTRIBUTED SYSTEMS
A3: Country | B3: University | C3: Professor | D3: Department | E3: Primary Research Areas | F3: Fit % | G3: Tier | H3: Recruitment Status | I3: Official Profile URL | J3: Verified Freshness
A4: United Kingdom | B4: University of Cambridge | C4: Prof. Jon Crowcroft | D4: Department of Computer Science and Technology | E4: Decentralized Edge Systems, Pervasive Computing, Privacy-Preserving Edge AI | F4: 97.5% | G4: Tier 1 | H4: CONFIRMED_ACTIVE | I4: https://www.cl.cam.ac.uk/~jac22/ | J4: 2026-09-15
A5: United Kingdom | B5: Imperial College London | C5: Prof. Julie A. McCann | D5: Department of Computing | E5: Edge Computing, Low-Power Wireless Networks, Cyber-Physical Systems | F5: 96.0% | G5: Tier 1 | H5: CONFIRMED_ACTIVE | I5: https://www.imperial.ac.uk/people/j.mccann | J5: 2026-09-15
A6: United Kingdom | B6: Imperial College London | C6: Prof. Peter Pietzuch | D6: Department of Computing | E6: Large-Scale Distributed Systems, Confidential Computing, Edge-Cloud Continuum | F6: 98.0% | G6: Tier 1 | H6: CONFIRMED_ACTIVE | I6: https://www.imperial.ac.uk/people/prp | J6: 2026-09-15
A7: United Kingdom | B7: University of Edinburgh | C7: Prof. Mahesh Marina | D7: School of Informatics | E7: 5G/6G Mobile Edge Networks, Software-Defined Radio, Edge AI for Wireless Optimization | F7: 95.0% | G7: Tier 1 | H7: STRONG_EVIDENCE | I7: https://homepages.inf.ed.ac.uk/mmarina/ | J7: 2026-09-15
A8: United Kingdom | B8: Imperial College London | C8: Prof. Hamed Haddadi | D8: Dyson School of Design Engineering / Department of Computing | E8: Privacy-Preserving Edge Machine Learning, Internet of Things, On-Device Sensing | F8: 97.0% | G8: Tier 1 | H8: CONFIRMED_ACTIVE | I8: https://www.imperial.ac.uk/people/h.haddadi | J8: 2026-09-15
A9: United Kingdom | B9: University of Cambridge | C9: Prof. Cecilia Mascolo | D9: Department of Computer Science and Technology | E9: Mobile Edge Systems, On-Device Audio AI, Wearable Sensing | F9: 96.5% | G9: Tier 1 | H9: CONFIRMED_ACTIVE | I9: https://www.cl.cam.ac.uk/~cm542/ | J9: 2026-09-15
A10: United Kingdom | B10: University of Cambridge | C10: Dr. Eiko Yoneki | D10: Department of Computer Science and Technology | E10: Systems for Machine Learning, Edge AI Acceleration, Graph Neural Networks at Edge | F10: 95.5% | G10: Tier 1 | H10: CONFIRMED_ACTIVE | I10: https://www.cl.cam.ac.uk/~ey204/ | J10: 2026-09-15
A11: United Kingdom | B11: University of Glasgow | C11: Prof. Dimitrios Pezaros | D11: School of Computing Science | E11: Resilient Edge Computing, Software-Defined Networking, Edge Cloud Orchestration | F11: 93.0% | G11: Tier 1 | H11: STRONG_EVIDENCE | I11: https://www.gla.ac.uk/schools/computing/staff/dimitriospezaros/ | J11: 2026-09-15
A12: United Kingdom | B12: University of Surrey / King's College London | C12: Prof. Nishanth Sastry | D12: Department of Computer Science / Informatics | E12: Edge Caching, Content Distribution Networks, Distributed Systems | F12: 94.0% | G12: Tier 1 | H12: STRONG_EVIDENCE | I12: https://www.surrey.ac.uk/people/nishanth-sastry | J12: 2026-09-15
A13: Japan | B13: The University of Tokyo / IIJ Research Lab | C13: Prof. Kenjiro Cho | D13: Graduate School of Information Science and Technology | E13: Internet Architecture, Edge Traffic Measurement, Network Observability | F13: 96.0% | G13: Tier 1 | H13: CONFIRMED_ACTIVE | I13: https://www.iijlab.net/~kjc/ | J13: 2026-09-15
A14: Japan | B14: The University of Tokyo | C14: Prof. Hiroshi Esaki | D14: Graduate School of Information Science and Technology | E14: Smart Building Edge Computing, Internet of Things, IPv6 Architecture | F14: 95.0% | G14: Tier 1 | H14: CONFIRMED_ACTIVE | I14: https://www.hongo.wide.ad.jp/ | J14: 2026-09-15
... A65: Hong Kong | B65: The Education University of Hong Kong | C65: Prof. Philip L.H. Yu | D65: Department of Mathematics and Information Technology (MIT) | E65: Statistical Machine Learning, Distributed IoT Stream Analytics, Anomaly Detection | F65: 78.0% | G65: Tier 3 | H65: POSSIBLE | I65: https://www.eduhk.hk/mit/people/academic-staff/yu-leung-ho-philip | J65: 2026-09-01

Sheet Global PhD Funding
A1: GLOBAL DOCTORAL FUNDING & SCHOLARSHIPS DIRECTORY
A3: Country | B3: University / Provider | C3: Scheme Title | D3: Funding Type | E3: Tuition Coverage | F3: Stipend / Salary | G3: International Access | H3: Dependant Support | I3: Application Deadline
A4: United Kingdom | B4: All UKRI-Partnered Universities (Imperial, Cambridge, Oxford, Edinburgh, etc.) | C4: UKRI / EPSRC Doctoral Studentships (DTP / ICASE / CDT) | D4: FULLY_FUNDED | E4: Full tuition fees covered for standard PhD duration (including international fee waivers within quota) | F4: £19,237/year minimum UKRI tax-free stipend (higher rate of ~£21,500/year for London institutions) + research travel grant | G4: ELIGIBLE | H4: PERMITTED | I4: 2026-12-15
A5: United Kingdom | B5: University of Cambridge | C5: Gates Cambridge Scholarship (PhD Track) | D5: FULLY_FUNDED | E5: Full Cambridge University Composition Fee covered | F5: £21,000/year tax-free maintenance allowance + up to £11,604/year family allowance for dependants | G5: ELIGIBLE | H5: EXCELLENT | I5: 2026-12-03
A6: United Kingdom | B6: Imperial College London | C6: Imperial College President's PhD Scholarships | D6: FULLY_FUNDED | E6: Full international or home tuition fees covered | F6: £25,150/year tax-free stipend + £2,000/year consumables fund | G6: ELIGIBLE | H6: PERMITTED | I6: 2026-11-06
A7: United Kingdom | B7: University of Edinburgh | C7: Principal's Career Development PhD Scholarships | D7: FULLY_FUNDED | E7: Full tuition fees at UK or Overseas rate | F7: £19,237/year stipend matching UKRI rate | G7: ELIGIBLE | H7: PERMITTED | I7: 2026-12-01
A8: Japan | B8: All Designated National Universities (UTokyo, Kyoto, Tokyo Tech, Osaka, Keio, etc.) | C8: Japanese Government (MEXT) Doctoral Scholarship (University & Embassy Track) | D8: FULLY_FUNDED | E8: Full 100% waiver of university examination, admission, and tuition fees | F8: 145,000 - 148,000 JPY/month tax-free living allowance + roundtrip international airfare | G8: ELIGIBLE | H8: PERMITTED | I8: 2026-11-30
A9: Japan | B9: All Japanese Universities & Research Institutes | C9: JSPS Research Fellowship for Young Scientists (DC1 / DC2) | D9: FULLY_FUNDED | E9: Institutional tuition waiver or subsidy typically granted to awardees | F9: 200,000 JPY/month monthly research stipend + up to 1,500,000 JPY/year Grants-in-Aid for Scientific Research (KAKENHI) | G9: ELIGIBLE | H9: PERMITTED | I9: 2026-05-15
A10: Japan | B10: The University of Tokyo | C10: The University of Tokyo Special Scholarship for International Students (UTokyo Fellowship) | D10: FULLY_FUNDED | E10: Full tuition fees covered through institutional grants | F10: 150,000 - 200,000 JPY/month research grant stipend | G10: ELIGIBLE | H10: PERMITTED | I10: 2026-11-15
A11: Japan | B11: Partner Japanese Universities (Kyoto, Tokyo Tech, Osaka, Keio, Tohoku) | C11: JST SPRING Doctoral Research Fellowship | D11: FULLY_FUNDED | E11: Full tuition exemption or institutional coverage | F11: 180,000 - 200,000 JPY/month living grant + 300,000 - 500,000 JPY/year research budget | G11: ELIGIBLE | H11: PERMITTED | I11: 2026-12-01
A12: Germany | B12: All German Public Universities (TUM, RWTH Aachen, TU Berlin, KIT, TU Dresden, etc.) | C12: TV-L E13 Research Associate (Wissenschaftlicher Mitarbeiter / Doctoral Position) | D12: FULLY_FUNDED | E12: Full tuition-free education (German public universities charge zero tuition; only nominal semester fee ~€150-€350 including transit pass) | F12: €48,000 - €56,000 gross/year (100% TV-L E13 salary) or €36,000 - €42,000 (75% TV-L E13), including full health, unemployment, and statutory pension insurance | G12: ELIGIBLE | H12: EXCELLENT | I12: 2026-12-01
A13: Germany | B13: All Accredited German Universities / Max Planck / Helmholtz Institutes | C13: DAAD Doctoral Research Grants (One-Year Grants / Complete Doctorate) | D13: FULLY_FUNDED | E13: Zero tuition at German universities; DAAD covers all mandatory semester contributions | F13: €1,350/month tax-free stipend + €460/year research allowance + monthly spouse/child supplement (€276/mo spouse + €204/mo child) + comprehensive health insurance | G13: ELIGIBLE | H13: EXCELLENT | I13: 2026-11-01
A14: Germany | B14: Participating DFG Research Training Groups (TUM, RWTH, TU Dresden, etc.) | C14: DFG Research Training Group (Graduiertenkolleg) Doctoral Positions | D14: FULLY_FUNDED | E14: Zero tuition + travel grants + workshop subsidies | F14: Full TV-L E13 employment contract (~€50,000/yr gross) or tax-free DFG doctoral fellowship (~€1,600/mo + child allowances) | G14: ELIGIBLE | H14: EXCELLENT | I14: 2026-12-15
... A30: Hong Kong | B30: The Education University of Hong Kong | C30: EdUHK Research Postgraduate Studentship (RPgS) | D30: FULLY_FUNDED | E30: Tuition waivers available for distinguished students | F30: Monthly studentship of HK$18,200 (or HK$27,600 for HKPFS awardees) | G30: ELIGIBLE | H30: PERMITTED | I30: 2026-12-01 23:59:59 HKT
